<?xml version="1.0" encoding="UTF-8"?>
<RegionsOfInterest version="1.1">
  <Region name="Air3_4000_1" color="0,255,0">
    <GeometryDef>
      <CoordSysStr>GEOGCS["GCS_WGS_1984",DATUM["D_WGS_1984",SPHEROID["WGS_1984",6378137.0,298.257223563]],PRIMEM["Greenwich",0.0],UNIT["Degree",0.0174532925199433]]</CoordSysStr>
      <Polygon>
        <Exterior>
          <LinearRing>
            <Coordinates>
-67.99876733 44.73519633 -67.99863871 44.73529258 -67.99857441 44.73519633 -67.998658 44.73512986 -67.99875125 44.73512757 -67.99876733 44.73515507 -67.99876733 44.73519633
            </Coordinates>
          </LinearRing>
        </Exterior>
      </Polygon>
    </GeometryDef>
  </Region>
  <Region name="Air3_4000_2" color="0,255,0">
    <GeometryDef>
      <CoordSysStr>GEOGCS["GCS_WGS_1984",DATUM["D_WGS_1984",SPHEROID["WGS_1984",6378137.0,298.257223563]],PRIMEM["Greenwich",0.0],UNIT["Degree",0.0174532925199433]]</CoordSysStr>
      <Polygon>
        <Exterior>
          <LinearRing>
            <Coordinates>
-67.99821107 44.73532696 -67.99806317 44.73535217 -67.99804709 44.73530404 -67.99813712 44.73526737 -67.99821107 44.735288 -67.99821107 44.73532696
            </Coordinates>
          </LinearRing>
        </Exterior>
      </Polygon>
    </GeometryDef>
  </Region>
</RegionsOfInterest>
