<PAMDataset>
  <PAMRasterBand band="1">
    <Metadata>
      <MDI key="STATISTICS_MAXIMUM">0.089419409632683</MDI>
      <MDI key="STATISTICS_MEAN">1.#SNAN</MDI>
      <MDI key="STATISTICS_MINIMUM">0</MDI>
      <MDI key="STATISTICS_STDDEV">1.#SNAN</MDI>
    </Metadata>
  </PAMRasterBand>
  <PAMRasterBand band="2">
    <Metadata>
      <MDI key="STATISTICS_MAXIMUM">0.080310858786106</MDI>
      <MDI key="STATISTICS_MEAN">1.#SNAN</MDI>
      <MDI key="STATISTICS_MINIMUM">-0.0062446212396026</MDI>
      <MDI key="STATISTICS_STDDEV">1.#SNAN</MDI>
    </Metadata>
  </PAMRasterBand>
  <PAMRasterBand band="3">
    <Metadata>
      <MDI key="STATISTICS_MAXIMUM">0.072624407708645</MDI>
      <MDI key="STATISTICS_MEAN">1.#SNAN</MDI>
      <MDI key="STATISTICS_MINIMUM">0</MDI>
      <MDI key="STATISTICS_STDDEV">1.#SNAN</MDI>
    </Metadata>
  </PAMRasterBand>
  <PAMRasterBand band="4">
    <Metadata>
      <MDI key="STATISTICS_MAXIMUM">0.056608416140079</MDI>
      <MDI key="STATISTICS_MEAN">1.#SNAN</MDI>
      <MDI key="STATISTICS_MINIMUM">-0.012437493540347</MDI>
      <MDI key="STATISTICS_STDDEV">1.#SNAN</MDI>
    </Metadata>
  </PAMRasterBand>
  <PAMRasterBand band="5">
    <Metadata>
      <MDI key="STATISTICS_MAXIMUM">0.062199518084526</MDI>
      <MDI key="STATISTICS_MEAN">1.#SNAN</MDI>
      <MDI key="STATISTICS_MINIMUM">0</MDI>
      <MDI key="STATISTICS_STDDEV">1.#SNAN</MDI>
    </Metadata>
  </PAMRasterBand>
  <PAMRasterBand band="6">
    <Metadata>
      <MDI key="STATISTICS_MAXIMUM">0.053672876209021</MDI>
      <MDI key="STATISTICS_MEAN">1.#SNAN</MDI>
      <MDI key="STATISTICS_MINIMUM">3.6476162368348e-011</MDI>
      <MDI key="STATISTICS_STDDEV">1.#SNAN</MDI>
    </Metadata>
  </PAMRasterBand>
  <PAMRasterBand band="7">
    <Metadata>
      <MDI key="STATISTICS_MAXIMUM">0.055068917572498</MDI>
      <MDI key="STATISTICS_MEAN">1.#SNAN</MDI>
      <MDI key="STATISTICS_MINIMUM">6.0722581110895e-005</MDI>
      <MDI key="STATISTICS_STDDEV">1.#SNAN</MDI>
    </Metadata>
  </PAMRasterBand>
  <PAMRasterBand band="8">
    <Metadata>
      <MDI key="STATISTICS_MAXIMUM">0.052111197263002</MDI>
      <MDI key="STATISTICS_MEAN">1.#SNAN</MDI>
      <MDI key="STATISTICS_MINIMUM">3.0985745979706e-005</MDI>
      <MDI key="STATISTICS_STDDEV">1.#SNAN</MDI>
    </Metadata>
  </PAMRasterBand>
  <PAMRasterBand band="9">
    <Metadata>
      <MDI key="STATISTICS_MAXIMUM">0.045146133750677</MDI>
      <MDI key="STATISTICS_MEAN">1.#SNAN</MDI>
      <MDI key="STATISTICS_MINIMUM">8.1820879131556e-005</MDI>
      <MDI key="STATISTICS_STDDEV">1.#SNAN</MDI>
    </Metadata>
  </PAMRasterBand>
  <PAMRasterBand band="10">
    <Metadata>
      <MDI key="STATISTICS_MAXIMUM">0.044623017311096</MDI>
      <MDI key="STATISTICS_MEAN">1.#SNAN</MDI>
      <MDI key="STATISTICS_MINIMUM">0.00025221859687008</MDI>
      <MDI key="STATISTICS_STDDEV">1.#SNAN</MDI>
    </Metadata>
  </PAMRasterBand>
  <PAMRasterBand band="11">
    <Metadata>
      <MDI key="STATISTICS_MAXIMUM">0.043329253792763</MDI>
      <MDI key="STATISTICS_MEAN">1.#SNAN</MDI>
      <MDI key="STATISTICS_MINIMUM">0.00028407739591785</MDI>
      <MDI key="STATISTICS_STDDEV">1.#SNAN</MDI>
    </Metadata>
  </PAMRasterBand>
  <PAMRasterBand band="12">
    <Metadata>
      <MDI key="STATISTICS_MAXIMUM">0.043715912848711</MDI>
      <MDI key="STATISTICS_MEAN">1.#SNAN</MDI>
      <MDI key="STATISTICS_MINIMUM">0.00017904461128637</MDI>
      <MDI key="STATISTICS_STDDEV">1.#SNAN</MDI>
    </Metadata>
  </PAMRasterBand>
  <PAMRasterBand band="13">
    <Metadata>
      <MDI key="STATISTICS_MAXIMUM">0.041662234812975</MDI>
      <MDI key="STATISTICS_MEAN">1.#SNAN</MDI>
      <MDI key="STATISTICS_MINIMUM">0.00091096723917872</MDI>
      <MDI key="STATISTICS_STDDEV">1.#SNAN</MDI>
    </Metadata>
  </PAMRasterBand>
  <PAMRasterBand band="14">
    <Metadata>
      <MDI key="STATISTICS_MAXIMUM">0.040697664022446</MDI>
      <MDI key="STATISTICS_MEAN">1.#SNAN</MDI>
      <MDI key="STATISTICS_MINIMUM">0.00076389708556235</MDI>
      <MDI key="STATISTICS_STDDEV">1.#SNAN</MDI>
    </Metadata>
  </PAMRasterBand>
  <PAMRasterBand band="15">
    <Metadata>
      <MDI key="STATISTICS_MAXIMUM">0.038563035428524</MDI>
      <MDI key="STATISTICS_MEAN">1.#SNAN</MDI>
      <MDI key="STATISTICS_MINIMUM">0.0019037279998884</MDI>
      <MDI key="STATISTICS_STDDEV">1.#SNAN</MDI>
    </Metadata>
  </PAMRasterBand>
  <PAMRasterBand band="16">
    <Metadata>
      <MDI key="STATISTICS_MAXIMUM">0.039567641913891</MDI>
      <MDI key="STATISTICS_MEAN">1.#SNAN</MDI>
      <MDI key="STATISTICS_MINIMUM">0.0027456877287477</MDI>
      <MDI key="STATISTICS_STDDEV">1.#SNAN</MDI>
    </Metadata>
  </PAMRasterBand>
  <PAMRasterBand band="17">
    <Metadata>
      <MDI key="STATISTICS_MAXIMUM">0.035829029977322</MDI>
      <MDI key="STATISTICS_MEAN">1.#SNAN</MDI>
      <MDI key="STATISTICS_MINIMUM">0.0005458066589199</MDI>
      <MDI key="STATISTICS_STDDEV">1.#SNAN</MDI>
    </Metadata>
  </PAMRasterBand>
  <PAMRasterBand band="18">
    <Metadata>
      <MDI key="STATISTICS_MAXIMUM">0.043684367090464</MDI>
      <MDI key="STATISTICS_MEAN">1.#SNAN</MDI>
      <MDI key="STATISTICS_MINIMUM">0.0020156367681921</MDI>
      <MDI key="STATISTICS_STDDEV">1.#SNAN</MDI>
    </Metadata>
  </PAMRasterBand>
  <PAMRasterBand band="19">
    <Metadata>
      <MDI key="STATISTICS_MAXIMUM">0.039725966751575</MDI>
      <MDI key="STATISTICS_MEAN">1.#SNAN</MDI>
      <MDI key="STATISTICS_MINIMUM">0.0063354750163853</MDI>
      <MDI key="STATISTICS_STDDEV">1.#SNAN</MDI>
    </Metadata>
  </PAMRasterBand>
  <PAMRasterBand band="20">
    <Metadata>
      <MDI key="STATISTICS_MAXIMUM">0.038306877017021</MDI>
      <MDI key="STATISTICS_MEAN">1.#SNAN</MDI>
      <MDI key="STATISTICS_MINIMUM">0.0067398101091385</MDI>
      <MDI key="STATISTICS_STDDEV">1.#SNAN</MDI>
    </Metadata>
  </PAMRasterBand>
  <PAMRasterBand band="21">
    <Metadata>
      <MDI key="STATISTICS_MAXIMUM">0.038464620709419</MDI>
      <MDI key="STATISTICS_MEAN">1.#SNAN</MDI>
      <MDI key="STATISTICS_MINIMUM">0.0049550854600966</MDI>
      <MDI key="STATISTICS_STDDEV">1.#SNAN</MDI>
    </Metadata>
  </PAMRasterBand>
  <PAMRasterBand band="22">
    <Metadata>
      <MDI key="STATISTICS_MAXIMUM">0.040377076715231</MDI>
      <MDI key="STATISTICS_MEAN">1.#SNAN</MDI>
      <MDI key="STATISTICS_MINIMUM">0.0094319926574826</MDI>
      <MDI key="STATISTICS_STDDEV">1.#SNAN</MDI>
    </Metadata>
  </PAMRasterBand>
  <PAMRasterBand band="23">
    <Metadata>
      <MDI key="STATISTICS_MAXIMUM">0.038251828402281</MDI>
      <MDI key="STATISTICS_MEAN">1.#SNAN</MDI>
      <MDI key="STATISTICS_MINIMUM">0.010115375742316</MDI>
      <MDI key="STATISTICS_STDDEV">1.#SNAN</MDI>
    </Metadata>
  </PAMRasterBand>
  <PAMRasterBand band="24">
    <Metadata>
      <MDI key="STATISTICS_MAXIMUM">0.037350654602051</MDI>
      <MDI key="STATISTICS_MEAN">1.#SNAN</MDI>
      <MDI key="STATISTICS_MINIMUM">0.0081577636301517</MDI>
      <MDI key="STATISTICS_STDDEV">1.#SNAN</MDI>
    </Metadata>
  </PAMRasterBand>
  <PAMRasterBand band="25">
    <Metadata>
      <MDI key="STATISTICS_MAXIMUM">0.037835910916328</MDI>
      <MDI key="STATISTICS_MEAN">1.#SNAN</MDI>
      <MDI key="STATISTICS_MINIMUM">0.010720960795879</MDI>
      <MDI key="STATISTICS_STDDEV">1.#SNAN</MDI>
    </Metadata>
  </PAMRasterBand>
  <PAMRasterBand band="26">
    <Metadata>
      <MDI key="STATISTICS_MAXIMUM">0.039039522409439</MDI>
      <MDI key="STATISTICS_MEAN">1.#SNAN</MDI>
      <MDI key="STATISTICS_MINIMUM">0.014288063161075</MDI>
      <MDI key="STATISTICS_STDDEV">1.#SNAN</MDI>
    </Metadata>
  </PAMRasterBand>
  <PAMRasterBand band="27">
    <Metadata>
      <MDI key="STATISTICS_MAXIMUM">0.037867017090321</MDI>
      <MDI key="STATISTICS_MEAN">1.#SNAN</MDI>
      <MDI key="STATISTICS_MINIMUM">0.01571193896234</MDI>
      <MDI key="STATISTICS_STDDEV">1.#SNAN</MDI>
    </Metadata>
  </PAMRasterBand>
  <PAMRasterBand band="28">
    <Metadata>
      <MDI key="STATISTICS_MAXIMUM">0.037625834345818</MDI>
      <MDI key="STATISTICS_MEAN">1.#SNAN</MDI>
      <MDI key="STATISTICS_MINIMUM">0.013457393273711</MDI>
      <MDI key="STATISTICS_STDDEV">1.#SNAN</MDI>
    </Metadata>
  </PAMRasterBand>
  <PAMRasterBand band="29">
    <Metadata>
      <MDI key="STATISTICS_MAXIMUM">0.040301222354174</MDI>
      <MDI key="STATISTICS_MEAN">1.#SNAN</MDI>
      <MDI key="STATISTICS_MINIMUM">0.017235232517123</MDI>
      <MDI key="STATISTICS_STDDEV">1.#SNAN</MDI>
    </Metadata>
  </PAMRasterBand>
  <PAMRasterBand band="30">
    <Metadata>
      <MDI key="STATISTICS_MAXIMUM">0.039723359048367</MDI>
      <MDI key="STATISTICS_MEAN">1.#SNAN</MDI>
      <MDI key="STATISTICS_MINIMUM">0.017415672540665</MDI>
      <MDI key="STATISTICS_STDDEV">1.#SNAN</MDI>
    </Metadata>
  </PAMRasterBand>
  <PAMRasterBand band="31">
    <Metadata>
      <MDI key="STATISTICS_MAXIMUM">0.042153466492891</MDI>
      <MDI key="STATISTICS_MEAN">1.#SNAN</MDI>
      <MDI key="STATISTICS_MINIMUM">0.016344364732504</MDI>
      <MDI key="STATISTICS_STDDEV">1.#SNAN</MDI>
    </Metadata>
  </PAMRasterBand>
  <PAMRasterBand band="32">
    <Metadata>
      <MDI key="STATISTICS_MAXIMUM">0.041884433478117</MDI>
      <MDI key="STATISTICS_MEAN">1.#SNAN</MDI>
      <MDI key="STATISTICS_MINIMUM">0.016094101592898</MDI>
      <MDI key="STATISTICS_STDDEV">1.#SNAN</MDI>
    </Metadata>
  </PAMRasterBand>
  <PAMRasterBand band="33">
    <Metadata>
      <MDI key="STATISTICS_MAXIMUM">0.040567748248577</MDI>
      <MDI key="STATISTICS_MEAN">1.#SNAN</MDI>
      <MDI key="STATISTICS_MINIMUM">0.019194290041924</MDI>
      <MDI key="STATISTICS_STDDEV">1.#SNAN</MDI>
    </Metadata>
  </PAMRasterBand>
  <PAMRasterBand band="34">
    <Metadata>
      <MDI key="STATISTICS_MAXIMUM">0.040631622076035</MDI>
      <MDI key="STATISTICS_MEAN">1.#SNAN</MDI>
      <MDI key="STATISTICS_MINIMUM">0.01978281699121</MDI>
      <MDI key="STATISTICS_STDDEV">1.#SNAN</MDI>
    </Metadata>
  </PAMRasterBand>
  <PAMRasterBand band="35">
    <Metadata>
      <MDI key="STATISTICS_MAXIMUM">0.04079195484519</MDI>
      <MDI key="STATISTICS_MEAN">1.#SNAN</MDI>
      <MDI key="STATISTICS_MINIMUM">0.01551416143775</MDI>
      <MDI key="STATISTICS_STDDEV">1.#SNAN</MDI>
    </Metadata>
  </PAMRasterBand>
  <PAMRasterBand band="36">
    <Metadata>
      <MDI key="STATISTICS_MAXIMUM">0.039924159646034</MDI>
      <MDI key="STATISTICS_MEAN">1.#SNAN</MDI>
      <MDI key="STATISTICS_MINIMUM">0.020460849627852</MDI>
      <MDI key="STATISTICS_STDDEV">1.#SNAN</MDI>
    </Metadata>
  </PAMRasterBand>
  <PAMRasterBand band="37">
    <Metadata>
      <MDI key="STATISTICS_MAXIMUM">0.041231404989958</MDI>
      <MDI key="STATISTICS_MEAN">1.#SNAN</MDI>
      <MDI key="STATISTICS_MINIMUM">0.020964954048395</MDI>
      <MDI key="STATISTICS_STDDEV">1.#SNAN</MDI>
    </Metadata>
  </PAMRasterBand>
  <PAMRasterBand band="38">
    <Metadata>
      <MDI key="STATISTICS_MAXIMUM">0.039112973958254</MDI>
      <MDI key="STATISTICS_MEAN">1.#SNAN</MDI>
      <MDI key="STATISTICS_MINIMUM">0.018667904660106</MDI>
      <MDI key="STATISTICS_STDDEV">1.#SNAN</MDI>
    </Metadata>
  </PAMRasterBand>
  <PAMRasterBand band="39">
    <Metadata>
      <MDI key="STATISTICS_MAXIMUM">0.037820991128683</MDI>
      <MDI key="STATISTICS_MEAN">1.#SNAN</MDI>
      <MDI key="STATISTICS_MINIMUM">0.020447814837098</MDI>
      <MDI key="STATISTICS_STDDEV">1.#SNAN</MDI>
    </Metadata>
  </PAMRasterBand>
  <PAMRasterBand band="40">
    <Metadata>
      <MDI key="STATISTICS_MAXIMUM">0.038266401737928</MDI>
      <MDI key="STATISTICS_MEAN">1.#SNAN</MDI>
      <MDI key="STATISTICS_MINIMUM">0.018446961417794</MDI>
      <MDI key="STATISTICS_STDDEV">1.#SNAN</MDI>
    </Metadata>
  </PAMRasterBand>
  <PAMRasterBand band="41">
    <Metadata>
      <MDI key="STATISTICS_MAXIMUM">0.038688492029905</MDI>
      <MDI key="STATISTICS_MEAN">1.#SNAN</MDI>
      <MDI key="STATISTICS_MINIMUM">0.019745672121644</MDI>
      <MDI key="STATISTICS_STDDEV">1.#SNAN</MDI>
    </Metadata>
  </PAMRasterBand>
  <PAMRasterBand band="42">
    <Metadata>
      <MDI key="STATISTICS_MAXIMUM">0.041329365223646</MDI>
      <MDI key="STATISTICS_MEAN">1.#SNAN</MDI>
      <MDI key="STATISTICS_MINIMUM">0.019611673429608</MDI>
      <MDI key="STATISTICS_STDDEV">1.#SNAN</MDI>
    </Metadata>
  </PAMRasterBand>
  <PAMRasterBand band="43">
    <Metadata>
      <MDI key="STATISTICS_MAXIMUM">0.038662802428007</MDI>
      <MDI key="STATISTICS_MEAN">1.#SNAN</MDI>
      <MDI key="STATISTICS_MINIMUM">0.020450677722692</MDI>
      <MDI key="STATISTICS_STDDEV">1.#SNAN</MDI>
    </Metadata>
  </PAMRasterBand>
  <PAMRasterBand band="44">
    <Metadata>
      <MDI key="STATISTICS_MAXIMUM">0.038286235183477</MDI>
      <MDI key="STATISTICS_MEAN">1.#SNAN</MDI>
      <MDI key="STATISTICS_MINIMUM">0.020560789853334</MDI>
      <MDI key="STATISTICS_STDDEV">1.#SNAN</MDI>
    </Metadata>
  </PAMRasterBand>
  <PAMRasterBand band="45">
    <Metadata>
      <MDI key="STATISTICS_MAXIMUM">0.040129367262125</MDI>
      <MDI key="STATISTICS_MEAN">1.#SNAN</MDI>
      <MDI key="STATISTICS_MINIMUM">0.022997532039881</MDI>
      <MDI key="STATISTICS_STDDEV">1.#SNAN</MDI>
    </Metadata>
  </PAMRasterBand>
  <PAMRasterBand band="46">
    <Metadata>
      <MDI key="STATISTICS_MAXIMUM">0.038377560675144</MDI>
      <MDI key="STATISTICS_MEAN">1.#SNAN</MDI>
      <MDI key="STATISTICS_MINIMUM">0.021948920562863</MDI>
      <MDI key="STATISTICS_STDDEV">1.#SNAN</MDI>
    </Metadata>
  </PAMRasterBand>
  <PAMRasterBand band="47">
    <Metadata>
      <MDI key="STATISTICS_MAXIMUM">0.040567427873611</MDI>
      <MDI key="STATISTICS_MEAN">1.#SNAN</MDI>
      <MDI key="STATISTICS_MINIMUM">0.022216325625777</MDI>
      <MDI key="STATISTICS_STDDEV">1.#SNAN</MDI>
    </Metadata>
  </PAMRasterBand>
  <PAMRasterBand band="48">
    <Metadata>
      <MDI key="STATISTICS_MAXIMUM">0.043056353926659</MDI>
      <MDI key="STATISTICS_MEAN">1.#SNAN</MDI>
      <MDI key="STATISTICS_MINIMUM">0.023783456534147</MDI>
      <MDI key="STATISTICS_STDDEV">1.#SNAN</MDI>
    </Metadata>
  </PAMRasterBand>
  <PAMRasterBand band="49">
    <Metadata>
      <MDI key="STATISTICS_MAXIMUM">0.040509816259146</MDI>
      <MDI key="STATISTICS_MEAN">1.#SNAN</MDI>
      <MDI key="STATISTICS_MINIMUM">0.022827113047242</MDI>
      <MDI key="STATISTICS_STDDEV">1.#SNAN</MDI>
    </Metadata>
  </PAMRasterBand>
  <PAMRasterBand band="50">
    <Metadata>
      <MDI key="STATISTICS_MAXIMUM">0.043537002056837</MDI>
      <MDI key="STATISTICS_MEAN">1.#SNAN</MDI>
      <MDI key="STATISTICS_MINIMUM">0.022616079077125</MDI>
      <MDI key="STATISTICS_STDDEV">1.#SNAN</MDI>
    </Metadata>
  </PAMRasterBand>
  <PAMRasterBand band="51">
    <Metadata>
      <MDI key="STATISTICS_MAXIMUM">0.043364353477955</MDI>
      <MDI key="STATISTICS_MEAN">1.#SNAN</MDI>
      <MDI key="STATISTICS_MINIMUM">0.022511238232255</MDI>
      <MDI key="STATISTICS_STDDEV">1.#SNAN</MDI>
    </Metadata>
  </PAMRasterBand>
  <PAMRasterBand band="52">
    <Metadata>
      <MDI key="STATISTICS_MAXIMUM">0.044186539947987</MDI>
      <MDI key="STATISTICS_MEAN">1.#SNAN</MDI>
      <MDI key="STATISTICS_MINIMUM">0.022877041250467</MDI>
      <MDI key="STATISTICS_STDDEV">1.#SNAN</MDI>
    </Metadata>
  </PAMRasterBand>
  <PAMRasterBand band="53">
    <Metadata>
      <MDI key="STATISTICS_MAXIMUM">0.042668711394072</MDI>
      <MDI key="STATISTICS_MEAN">1.#SNAN</MDI>
      <MDI key="STATISTICS_MINIMUM">0.024344628676772</MDI>
      <MDI key="STATISTICS_STDDEV">1.#SNAN</MDI>
    </Metadata>
  </PAMRasterBand>
  <PAMRasterBand band="54">
    <Metadata>
      <MDI key="STATISTICS_MAXIMUM">0.045721765607595</MDI>
      <MDI key="STATISTICS_MEAN">1.#SNAN</MDI>
      <MDI key="STATISTICS_MINIMUM">0.024746710434556</MDI>
      <MDI key="STATISTICS_STDDEV">1.#SNAN</MDI>
    </Metadata>
  </PAMRasterBand>
  <PAMRasterBand band="55">
    <Metadata>
      <MDI key="STATISTICS_MAXIMUM">0.04895905405283</MDI>
      <MDI key="STATISTICS_MEAN">1.#SNAN</MDI>
      <MDI key="STATISTICS_MINIMUM">0.025876648724079</MDI>
      <MDI key="STATISTICS_STDDEV">1.#SNAN</MDI>
    </Metadata>
  </PAMRasterBand>
  <PAMRasterBand band="56">
    <Metadata>
      <MDI key="STATISTICS_MAXIMUM">0.047480225563049</MDI>
      <MDI key="STATISTICS_MEAN">1.#SNAN</MDI>
      <MDI key="STATISTICS_MINIMUM">0.027597362175584</MDI>
      <MDI key="STATISTICS_STDDEV">1.#SNAN</MDI>
    </Metadata>
  </PAMRasterBand>
  <PAMRasterBand band="57">
    <Metadata>
      <MDI key="STATISTICS_MAXIMUM">0.049763336777687</MDI>
      <MDI key="STATISTICS_MEAN">1.#SNAN</MDI>
      <MDI key="STATISTICS_MINIMUM">0.028361598029733</MDI>
      <MDI key="STATISTICS_STDDEV">1.#SNAN</MDI>
    </Metadata>
  </PAMRasterBand>
  <PAMRasterBand band="58">
    <Metadata>
      <MDI key="STATISTICS_MAXIMUM">0.051423344761133</MDI>
      <MDI key="STATISTICS_MEAN">1.#SNAN</MDI>
      <MDI key="STATISTICS_MINIMUM">0.03083455376327</MDI>
      <MDI key="STATISTICS_STDDEV">1.#SNAN</MDI>
    </Metadata>
  </PAMRasterBand>
  <PAMRasterBand band="59">
    <Metadata>
      <MDI key="STATISTICS_MAXIMUM">0.055229235440493</MDI>
      <MDI key="STATISTICS_MEAN">1.#SNAN</MDI>
      <MDI key="STATISTICS_MINIMUM">0.031084887683392</MDI>
      <MDI key="STATISTICS_STDDEV">1.#SNAN</MDI>
    </Metadata>
  </PAMRasterBand>
  <PAMRasterBand band="60">
    <Metadata>
      <MDI key="STATISTICS_MAXIMUM">0.05933303385973</MDI>
      <MDI key="STATISTICS_MEAN">1.#SNAN</MDI>
      <MDI key="STATISTICS_MINIMUM">0.031992539763451</MDI>
      <MDI key="STATISTICS_STDDEV">1.#SNAN</MDI>
    </Metadata>
  </PAMRasterBand>
  <PAMRasterBand band="61">
    <Metadata>
      <MDI key="STATISTICS_MAXIMUM">0.061308145523071</MDI>
      <MDI key="STATISTICS_MEAN">1.#SNAN</MDI>
      <MDI key="STATISTICS_MINIMUM">0.03504791483283</MDI>
      <MDI key="STATISTICS_STDDEV">1.#SNAN</MDI>
    </Metadata>
  </PAMRasterBand>
  <PAMRasterBand band="62">
    <Metadata>
      <MDI key="STATISTICS_MAXIMUM">0.067023918032646</MDI>
      <MDI key="STATISTICS_MEAN">1.#SNAN</MDI>
      <MDI key="STATISTICS_MINIMUM">0.043264981359243</MDI>
      <MDI key="STATISTICS_STDDEV">1.#SNAN</MDI>
    </Metadata>
  </PAMRasterBand>
  <PAMRasterBand band="63">
    <Metadata>
      <MDI key="STATISTICS_MAXIMUM">0.071825176477432</MDI>
      <MDI key="STATISTICS_MEAN">1.#SNAN</MDI>
      <MDI key="STATISTICS_MINIMUM">0.045821327716112</MDI>
      <MDI key="STATISTICS_STDDEV">1.#SNAN</MDI>
    </Metadata>
  </PAMRasterBand>
  <PAMRasterBand band="64">
    <Metadata>
      <MDI key="STATISTICS_MAXIMUM">0.081186793744564</MDI>
      <MDI key="STATISTICS_MEAN">1.#SNAN</MDI>
      <MDI key="STATISTICS_MINIMUM">0.047523502260447</MDI>
      <MDI key="STATISTICS_STDDEV">1.#SNAN</MDI>
    </Metadata>
  </PAMRasterBand>
  <PAMRasterBand band="65">
    <Metadata>
      <MDI key="STATISTICS_MAXIMUM">0.086568661034107</MDI>
      <MDI key="STATISTICS_MEAN">1.#SNAN</MDI>
      <MDI key="STATISTICS_MINIMUM">0.056450139731169</MDI>
      <MDI key="STATISTICS_STDDEV">1.#SNAN</MDI>
    </Metadata>
  </PAMRasterBand>
  <PAMRasterBand band="66">
    <Metadata>
      <MDI key="STATISTICS_MAXIMUM">0.09394758194685</MDI>
      <MDI key="STATISTICS_MEAN">1.#SNAN</MDI>
      <MDI key="STATISTICS_MINIMUM">0.059239629656076</MDI>
      <MDI key="STATISTICS_STDDEV">1.#SNAN</MDI>
    </Metadata>
  </PAMRasterBand>
  <PAMRasterBand band="67">
    <Metadata>
      <MDI key="STATISTICS_MAXIMUM">0.097476340830326</MDI>
      <MDI key="STATISTICS_MEAN">1.#SNAN</MDI>
      <MDI key="STATISTICS_MINIMUM">0.06450243294239</MDI>
      <MDI key="STATISTICS_STDDEV">1.#SNAN</MDI>
    </Metadata>
  </PAMRasterBand>
  <PAMRasterBand band="68">
    <Metadata>
      <MDI key="STATISTICS_MAXIMUM">0.10758654773235</MDI>
      <MDI key="STATISTICS_MEAN">1.#SNAN</MDI>
      <MDI key="STATISTICS_MINIMUM">0.073209397494793</MDI>
      <MDI key="STATISTICS_STDDEV">1.#SNAN</MDI>
    </Metadata>
  </PAMRasterBand>
  <PAMRasterBand band="69">
    <Metadata>
      <MDI key="STATISTICS_MAXIMUM">0.11758255213499</MDI>
      <MDI key="STATISTICS_MEAN">1.#SNAN</MDI>
      <MDI key="STATISTICS_MINIMUM">0.078892529010773</MDI>
      <MDI key="STATISTICS_STDDEV">1.#SNAN</MDI>
    </Metadata>
  </PAMRasterBand>
  <PAMRasterBand band="70">
    <Metadata>
      <MDI key="STATISTICS_MAXIMUM">0.12300052493811</MDI>
      <MDI key="STATISTICS_MEAN">1.#SNAN</MDI>
      <MDI key="STATISTICS_MINIMUM">0.086106330156326</MDI>
      <MDI key="STATISTICS_STDDEV">1.#SNAN</MDI>
    </Metadata>
  </PAMRasterBand>
  <PAMRasterBand band="71">
    <Metadata>
      <MDI key="STATISTICS_MAXIMUM">0.13283732533455</MDI>
      <MDI key="STATISTICS_MEAN">1.#SNAN</MDI>
      <MDI key="STATISTICS_MINIMUM">0.090388581156731</MDI>
      <MDI key="STATISTICS_STDDEV">1.#SNAN</MDI>
    </Metadata>
  </PAMRasterBand>
  <PAMRasterBand band="72">
    <Metadata>
      <MDI key="STATISTICS_MAXIMUM">0.14066438376904</MDI>
      <MDI key="STATISTICS_MEAN">1.#SNAN</MDI>
      <MDI key="STATISTICS_MINIMUM">0.09567292034626</MDI>
      <MDI key="STATISTICS_STDDEV">1.#SNAN</MDI>
    </Metadata>
  </PAMRasterBand>
  <PAMRasterBand band="73">
    <Metadata>
      <MDI key="STATISTICS_MAXIMUM">0.14767205715179</MDI>
      <MDI key="STATISTICS_MEAN">1.#SNAN</MDI>
      <MDI key="STATISTICS_MINIMUM">0.10518281906843</MDI>
      <MDI key="STATISTICS_STDDEV">1.#SNAN</MDI>
    </Metadata>
  </PAMRasterBand>
  <PAMRasterBand band="74">
    <Metadata>
      <MDI key="STATISTICS_MAXIMUM">0.15936855971813</MDI>
      <MDI key="STATISTICS_MEAN">1.#SNAN</MDI>
      <MDI key="STATISTICS_MINIMUM">0.10780349373817</MDI>
      <MDI key="STATISTICS_STDDEV">1.#SNAN</MDI>
    </Metadata>
  </PAMRasterBand>
  <PAMRasterBand band="75">
    <Metadata>
      <MDI key="STATISTICS_MAXIMUM">0.15982933342457</MDI>
      <MDI key="STATISTICS_MEAN">1.#SNAN</MDI>
      <MDI key="STATISTICS_MINIMUM">0.11161084473133</MDI>
      <MDI key="STATISTICS_STDDEV">1.#SNAN</MDI>
    </Metadata>
  </PAMRasterBand>
  <PAMRasterBand band="76">
    <Metadata>
      <MDI key="STATISTICS_MAXIMUM">0.16761419177055</MDI>
      <MDI key="STATISTICS_MEAN">1.#SNAN</MDI>
      <MDI key="STATISTICS_MINIMUM">0.11833587288857</MDI>
      <MDI key="STATISTICS_STDDEV">1.#SNAN</MDI>
    </Metadata>
  </PAMRasterBand>
  <PAMRasterBand band="77">
    <Metadata>
      <MDI key="STATISTICS_MAXIMUM">0.16757346689701</MDI>
      <MDI key="STATISTICS_MEAN">1.#SNAN</MDI>
      <MDI key="STATISTICS_MINIMUM">0.12049636244774</MDI>
      <MDI key="STATISTICS_STDDEV">1.#SNAN</MDI>
    </Metadata>
  </PAMRasterBand>
  <PAMRasterBand band="78">
    <Metadata>
      <MDI key="STATISTICS_MAXIMUM">0.17553173005581</MDI>
      <MDI key="STATISTICS_MEAN">1.#SNAN</MDI>
      <MDI key="STATISTICS_MINIMUM">0.12682001292706</MDI>
      <MDI key="STATISTICS_STDDEV">1.#SNAN</MDI>
    </Metadata>
  </PAMRasterBand>
  <PAMRasterBand band="79">
    <Metadata>
      <MDI key="STATISTICS_MAXIMUM">0.17960971593857</MDI>
      <MDI key="STATISTICS_MEAN">1.#SNAN</MDI>
      <MDI key="STATISTICS_MINIMUM">0.12528602778912</MDI>
      <MDI key="STATISTICS_STDDEV">1.#SNAN</MDI>
    </Metadata>
  </PAMRasterBand>
  <PAMRasterBand band="80">
    <Metadata>
      <MDI key="STATISTICS_MAXIMUM">0.17981973290443</MDI>
      <MDI key="STATISTICS_MEAN">1.#SNAN</MDI>
      <MDI key="STATISTICS_MINIMUM">0.1287616789341</MDI>
      <MDI key="STATISTICS_STDDEV">1.#SNAN</MDI>
    </Metadata>
  </PAMRasterBand>
  <PAMRasterBand band="81">
    <Metadata>
      <MDI key="STATISTICS_MAXIMUM">0.18366619944572</MDI>
      <MDI key="STATISTICS_MEAN">1.#SNAN</MDI>
      <MDI key="STATISTICS_MINIMUM">0.12817372381687</MDI>
      <MDI key="STATISTICS_STDDEV">1.#SNAN</MDI>
    </Metadata>
  </PAMRasterBand>
  <PAMRasterBand band="82">
    <Metadata>
      <MDI key="STATISTICS_MAXIMUM">0.18817992508411</MDI>
      <MDI key="STATISTICS_MEAN">1.#SNAN</MDI>
      <MDI key="STATISTICS_MINIMUM">0.13343641161919</MDI>
      <MDI key="STATISTICS_STDDEV">1.#SNAN</MDI>
    </Metadata>
  </PAMRasterBand>
  <PAMRasterBand band="83">
    <Metadata>
      <MDI key="STATISTICS_MAXIMUM">0.19208437204361</MDI>
      <MDI key="STATISTICS_MEAN">1.#SNAN</MDI>
      <MDI key="STATISTICS_MINIMUM">0.13142809271812</MDI>
      <MDI key="STATISTICS_STDDEV">1.#SNAN</MDI>
    </Metadata>
  </PAMRasterBand>
  <PAMRasterBand band="84">
    <Metadata>
      <MDI key="STATISTICS_MAXIMUM">0.18982921540737</MDI>
      <MDI key="STATISTICS_MEAN">1.#SNAN</MDI>
      <MDI key="STATISTICS_MINIMUM">0.13443541526794</MDI>
      <MDI key="STATISTICS_STDDEV">1.#SNAN</MDI>
    </Metadata>
  </PAMRasterBand>
  <PAMRasterBand band="85">
    <Metadata>
      <MDI key="STATISTICS_MAXIMUM">0.1965779364109</MDI>
      <MDI key="STATISTICS_MEAN">1.#SNAN</MDI>
      <MDI key="STATISTICS_MINIMUM">0.1367994248867</MDI>
      <MDI key="STATISTICS_STDDEV">1.#SNAN</MDI>
    </Metadata>
  </PAMRasterBand>
  <PAMRasterBand band="86">
    <Metadata>
      <MDI key="STATISTICS_MAXIMUM">0.19652761518955</MDI>
      <MDI key="STATISTICS_MEAN">1.#SNAN</MDI>
      <MDI key="STATISTICS_MINIMUM">0.13729640841484</MDI>
      <MDI key="STATISTICS_STDDEV">1.#SNAN</MDI>
    </Metadata>
  </PAMRasterBand>
  <PAMRasterBand band="87">
    <Metadata>
      <MDI key="STATISTICS_MAXIMUM">0.19545190036297</MDI>
      <MDI key="STATISTICS_MEAN">1.#SNAN</MDI>
      <MDI key="STATISTICS_MINIMUM">0.14134854078293</MDI>
      <MDI key="STATISTICS_STDDEV">1.#SNAN</MDI>
    </Metadata>
  </PAMRasterBand>
  <PAMRasterBand band="88">
    <Metadata>
      <MDI key="STATISTICS_MAXIMUM">0.19451473653316</MDI>
      <MDI key="STATISTICS_MEAN">1.#SNAN</MDI>
      <MDI key="STATISTICS_MINIMUM">0.13637268543243</MDI>
      <MDI key="STATISTICS_STDDEV">1.#SNAN</MDI>
    </Metadata>
  </PAMRasterBand>
  <PAMRasterBand band="89">
    <Metadata>
      <MDI key="STATISTICS_MAXIMUM">0.19533379375935</MDI>
      <MDI key="STATISTICS_MEAN">1.#SNAN</MDI>
      <MDI key="STATISTICS_MINIMUM">0.14097362756729</MDI>
      <MDI key="STATISTICS_STDDEV">1.#SNAN</MDI>
    </Metadata>
  </PAMRasterBand>
  <PAMRasterBand band="90">
    <Metadata>
      <MDI key="STATISTICS_MAXIMUM">0.19468820095062</MDI>
      <MDI key="STATISTICS_MEAN">1.#SNAN</MDI>
      <MDI key="STATISTICS_MINIMUM">0.13292190432549</MDI>
      <MDI key="STATISTICS_STDDEV">1.#SNAN</MDI>
    </Metadata>
  </PAMRasterBand>
  <PAMRasterBand band="91">
    <Metadata>
      <MDI key="STATISTICS_MAXIMUM">0.19050487875938</MDI>
      <MDI key="STATISTICS_MEAN">1.#SNAN</MDI>
      <MDI key="STATISTICS_MINIMUM">0.12971216440201</MDI>
      <MDI key="STATISTICS_STDDEV">1.#SNAN</MDI>
    </Metadata>
  </PAMRasterBand>
  <PAMRasterBand band="92">
    <Metadata>
      <MDI key="STATISTICS_MAXIMUM">0.18605677783489</MDI>
      <MDI key="STATISTICS_MEAN">1.#SNAN</MDI>
      <MDI key="STATISTICS_MINIMUM">0.12977024912834</MDI>
      <MDI key="STATISTICS_STDDEV">1.#SNAN</MDI>
    </Metadata>
  </PAMRasterBand>
  <PAMRasterBand band="93">
    <Metadata>
      <MDI key="STATISTICS_MAXIMUM">0.18614771962166</MDI>
      <MDI key="STATISTICS_MEAN">1.#SNAN</MDI>
      <MDI key="STATISTICS_MINIMUM">0.13080289959908</MDI>
      <MDI key="STATISTICS_STDDEV">1.#SNAN</MDI>
    </Metadata>
  </PAMRasterBand>
  <PAMRasterBand band="94">
    <Metadata>
      <MDI key="STATISTICS_MAXIMUM">0.18143813312054</MDI>
      <MDI key="STATISTICS_MEAN">1.#SNAN</MDI>
      <MDI key="STATISTICS_MINIMUM">0.12422427535057</MDI>
      <MDI key="STATISTICS_STDDEV">1.#SNAN</MDI>
    </Metadata>
  </PAMRasterBand>
  <PAMRasterBand band="95">
    <Metadata>
      <MDI key="STATISTICS_MAXIMUM">0.17715086042881</MDI>
      <MDI key="STATISTICS_MEAN">1.#SNAN</MDI>
      <MDI key="STATISTICS_MINIMUM">0.119553565979</MDI>
      <MDI key="STATISTICS_STDDEV">1.#SNAN</MDI>
    </Metadata>
  </PAMRasterBand>
  <PAMRasterBand band="96">
    <Metadata>
      <MDI key="STATISTICS_MAXIMUM">0.17297434806824</MDI>
      <MDI key="STATISTICS_MEAN">1.#SNAN</MDI>
      <MDI key="STATISTICS_MINIMUM">0.11754228174686</MDI>
      <MDI key="STATISTICS_STDDEV">1.#SNAN</MDI>
    </Metadata>
  </PAMRasterBand>
  <PAMRasterBand band="97">
    <Metadata>
      <MDI key="STATISTICS_MAXIMUM">0.16770403087139</MDI>
      <MDI key="STATISTICS_MEAN">1.#SNAN</MDI>
      <MDI key="STATISTICS_MINIMUM">0.1114569157362</MDI>
      <MDI key="STATISTICS_STDDEV">1.#SNAN</MDI>
    </Metadata>
  </PAMRasterBand>
  <PAMRasterBand band="98">
    <Metadata>
      <MDI key="STATISTICS_MAXIMUM">0.16303867101669</MDI>
      <MDI key="STATISTICS_MEAN">1.#SNAN</MDI>
      <MDI key="STATISTICS_MINIMUM">0.11169016361237</MDI>
      <MDI key="STATISTICS_STDDEV">1.#SNAN</MDI>
    </Metadata>
  </PAMRasterBand>
  <PAMRasterBand band="99">
    <Metadata>
      <MDI key="STATISTICS_MAXIMUM">0.15996135771275</MDI>
      <MDI key="STATISTICS_MEAN">1.#SNAN</MDI>
      <MDI key="STATISTICS_MINIMUM">0.11006741225719</MDI>
      <MDI key="STATISTICS_STDDEV">1.#SNAN</MDI>
    </Metadata>
  </PAMRasterBand>
  <PAMRasterBand band="100">
    <Metadata>
      <MDI key="STATISTICS_MAXIMUM">0.15754328668118</MDI>
      <MDI key="STATISTICS_MEAN">1.#SNAN</MDI>
      <MDI key="STATISTICS_MINIMUM">0.10511176288128</MDI>
      <MDI key="STATISTICS_STDDEV">1.#SNAN</MDI>
    </Metadata>
  </PAMRasterBand>
  <PAMRasterBand band="101">
    <Metadata>
      <MDI key="STATISTICS_MAXIMUM">0.15393370389938</MDI>
      <MDI key="STATISTICS_MEAN">1.#SNAN</MDI>
      <MDI key="STATISTICS_MINIMUM">0.099083371460438</MDI>
      <MDI key="STATISTICS_STDDEV">1.#SNAN</MDI>
    </Metadata>
  </PAMRasterBand>
  <PAMRasterBand band="102">
    <Metadata>
      <MDI key="STATISTICS_MAXIMUM">0.15440475940704</MDI>
      <MDI key="STATISTICS_MEAN">1.#SNAN</MDI>
      <MDI key="STATISTICS_MINIMUM">0.10414171218872</MDI>
      <MDI key="STATISTICS_STDDEV">1.#SNAN</MDI>
    </Metadata>
  </PAMRasterBand>
  <PAMRasterBand band="103">
    <Metadata>
      <MDI key="STATISTICS_MAXIMUM">0.15041403472424</MDI>
      <MDI key="STATISTICS_MEAN">1.#SNAN</MDI>
      <MDI key="STATISTICS_MINIMUM">0.096067830920219</MDI>
      <MDI key="STATISTICS_STDDEV">1.#SNAN</MDI>
    </Metadata>
  </PAMRasterBand>
  <PAMRasterBand band="104">
    <Metadata>
      <MDI key="STATISTICS_MAXIMUM">0.15249690413475</MDI>
      <MDI key="STATISTICS_MEAN">1.#SNAN</MDI>
      <MDI key="STATISTICS_MINIMUM">0.09721052646637</MDI>
      <MDI key="STATISTICS_STDDEV">1.#SNAN</MDI>
    </Metadata>
  </PAMRasterBand>
  <PAMRasterBand band="105">
    <Metadata>
      <MDI key="STATISTICS_MAXIMUM">0.15111735463142</MDI>
      <MDI key="STATISTICS_MEAN">1.#SNAN</MDI>
      <MDI key="STATISTICS_MINIMUM">0.095126293599606</MDI>
      <MDI key="STATISTICS_STDDEV">1.#SNAN</MDI>
    </Metadata>
  </PAMRasterBand>
  <PAMRasterBand band="106">
    <Metadata>
      <MDI key="STATISTICS_MAXIMUM">0.14417158067226</MDI>
      <MDI key="STATISTICS_MEAN">1.#SNAN</MDI>
      <MDI key="STATISTICS_MINIMUM">0.095380768179893</MDI>
      <MDI key="STATISTICS_STDDEV">1.#SNAN</MDI>
    </Metadata>
  </PAMRasterBand>
  <PAMRasterBand band="107">
    <Metadata>
      <MDI key="STATISTICS_MAXIMUM">0.14598244428635</MDI>
      <MDI key="STATISTICS_MEAN">1.#SNAN</MDI>
      <MDI key="STATISTICS_MINIMUM">0.096723198890686</MDI>
      <MDI key="STATISTICS_STDDEV">1.#SNAN</MDI>
    </Metadata>
  </PAMRasterBand>
  <PAMRasterBand band="108">
    <Metadata>
      <MDI key="STATISTICS_MAXIMUM">0.14392168819904</MDI>
      <MDI key="STATISTICS_MEAN">1.#SNAN</MDI>
      <MDI key="STATISTICS_MINIMUM">0.093185931444168</MDI>
      <MDI key="STATISTICS_STDDEV">1.#SNAN</MDI>
    </Metadata>
  </PAMRasterBand>
  <PAMRasterBand band="109">
    <Metadata>
      <MDI key="STATISTICS_MAXIMUM">0.14457592368126</MDI>
      <MDI key="STATISTICS_MEAN">1.#SNAN</MDI>
      <MDI key="STATISTICS_MINIMUM">0.092564955353737</MDI>
      <MDI key="STATISTICS_STDDEV">1.#SNAN</MDI>
    </Metadata>
  </PAMRasterBand>
  <PAMRasterBand band="110">
    <Metadata>
      <MDI key="STATISTICS_MAXIMUM">0.14255361258984</MDI>
      <MDI key="STATISTICS_MEAN">1.#SNAN</MDI>
      <MDI key="STATISTICS_MINIMUM">0.088565520942211</MDI>
      <MDI key="STATISTICS_STDDEV">1.#SNAN</MDI>
    </Metadata>
  </PAMRasterBand>
  <PAMRasterBand band="111">
    <Metadata>
      <MDI key="STATISTICS_MAXIMUM">0.14147505164146</MDI>
      <MDI key="STATISTICS_MEAN">1.#SNAN</MDI>
      <MDI key="STATISTICS_MINIMUM">0.091287456452847</MDI>
      <MDI key="STATISTICS_STDDEV">1.#SNAN</MDI>
    </Metadata>
  </PAMRasterBand>
  <PAMRasterBand band="112">
    <Metadata>
      <MDI key="STATISTICS_MAXIMUM">0.14023897051811</MDI>
      <MDI key="STATISTICS_MEAN">1.#SNAN</MDI>
      <MDI key="STATISTICS_MINIMUM">0.089828930795193</MDI>
      <MDI key="STATISTICS_STDDEV">1.#SNAN</MDI>
    </Metadata>
  </PAMRasterBand>
  <PAMRasterBand band="113">
    <Metadata>
      <MDI key="STATISTICS_MAXIMUM">0.14164850115776</MDI>
      <MDI key="STATISTICS_MEAN">1.#SNAN</MDI>
      <MDI key="STATISTICS_MINIMUM">0.087224133312702</MDI>
      <MDI key="STATISTICS_STDDEV">1.#SNAN</MDI>
    </Metadata>
  </PAMRasterBand>
  <PAMRasterBand band="114">
    <Metadata>
      <MDI key="STATISTICS_MAXIMUM">0.13475117087364</MDI>
      <MDI key="STATISTICS_MEAN">1.#SNAN</MDI>
      <MDI key="STATISTICS_MINIMUM">0.089340530335903</MDI>
      <MDI key="STATISTICS_STDDEV">1.#SNAN</MDI>
    </Metadata>
  </PAMRasterBand>
  <PAMRasterBand band="115">
    <Metadata>
      <MDI key="STATISTICS_MAXIMUM">0.13242709636688</MDI>
      <MDI key="STATISTICS_MEAN">1.#SNAN</MDI>
      <MDI key="STATISTICS_MINIMUM">0.087940141558647</MDI>
      <MDI key="STATISTICS_STDDEV">1.#SNAN</MDI>
    </Metadata>
  </PAMRasterBand>
  <PAMRasterBand band="116">
    <Metadata>
      <MDI key="STATISTICS_MAXIMUM">0.13113144040108</MDI>
      <MDI key="STATISTICS_MEAN">1.#SNAN</MDI>
      <MDI key="STATISTICS_MINIMUM">0.079297557473183</MDI>
      <MDI key="STATISTICS_STDDEV">1.#SNAN</MDI>
    </Metadata>
  </PAMRasterBand>
  <PAMRasterBand band="117">
    <Metadata>
      <MDI key="STATISTICS_MAXIMUM">0.13279615342617</MDI>
      <MDI key="STATISTICS_MEAN">1.#SNAN</MDI>
      <MDI key="STATISTICS_MINIMUM">0.078690819442272</MDI>
      <MDI key="STATISTICS_STDDEV">1.#SNAN</MDI>
    </Metadata>
  </PAMRasterBand>
  <PAMRasterBand band="118">
    <Metadata>
      <MDI key="STATISTICS_MAXIMUM">0.13232611119747</MDI>
      <MDI key="STATISTICS_MEAN">1.#SNAN</MDI>
      <MDI key="STATISTICS_MINIMUM">0.078482151031494</MDI>
      <MDI key="STATISTICS_STDDEV">1.#SNAN</MDI>
    </Metadata>
  </PAMRasterBand>
  <PAMRasterBand band="119">
    <Metadata>
      <MDI key="STATISTICS_MAXIMUM">0.12506248056889</MDI>
      <MDI key="STATISTICS_MEAN">1.#SNAN</MDI>
      <MDI key="STATISTICS_MINIMUM">0.076932847499847</MDI>
      <MDI key="STATISTICS_STDDEV">1.#SNAN</MDI>
    </Metadata>
  </PAMRasterBand>
  <PAMRasterBand band="120">
    <Metadata>
      <MDI key="STATISTICS_MAXIMUM">0.12451804429293</MDI>
      <MDI key="STATISTICS_MEAN">1.#SNAN</MDI>
      <MDI key="STATISTICS_MINIMUM">0.070944786071777</MDI>
      <MDI key="STATISTICS_STDDEV">1.#SNAN</MDI>
    </Metadata>
  </PAMRasterBand>
  <PAMRasterBand band="121">
    <Metadata>
      <MDI key="STATISTICS_MAXIMUM">0.12287646532059</MDI>
      <MDI key="STATISTICS_MEAN">1.#SNAN</MDI>
      <MDI key="STATISTICS_MINIMUM">0.074221439659595</MDI>
      <MDI key="STATISTICS_STDDEV">1.#SNAN</MDI>
    </Metadata>
  </PAMRasterBand>
  <PAMRasterBand band="122">
    <Metadata>
      <MDI key="STATISTICS_MAXIMUM">0.12016503512859</MDI>
      <MDI key="STATISTICS_MEAN">1.#SNAN</MDI>
      <MDI key="STATISTICS_MINIMUM">0.073208995163441</MDI>
      <MDI key="STATISTICS_STDDEV">1.#SNAN</MDI>
    </Metadata>
  </PAMRasterBand>
  <PAMRasterBand band="123">
    <Metadata>
      <MDI key="STATISTICS_MAXIMUM">0.12383971363306</MDI>
      <MDI key="STATISTICS_MEAN">1.#SNAN</MDI>
      <MDI key="STATISTICS_MINIMUM">0.073192186653614</MDI>
      <MDI key="STATISTICS_STDDEV">1.#SNAN</MDI>
    </Metadata>
  </PAMRasterBand>
  <PAMRasterBand band="124">
    <Metadata>
      <MDI key="STATISTICS_MAXIMUM">0.11918593943119</MDI>
      <MDI key="STATISTICS_MEAN">1.#SNAN</MDI>
      <MDI key="STATISTICS_MINIMUM">0.071590684354305</MDI>
      <MDI key="STATISTICS_STDDEV">1.#SNAN</MDI>
    </Metadata>
  </PAMRasterBand>
  <PAMRasterBand band="125">
    <Metadata>
      <MDI key="STATISTICS_MAXIMUM">0.11741182953119</MDI>
      <MDI key="STATISTICS_MEAN">1.#SNAN</MDI>
      <MDI key="STATISTICS_MINIMUM">0.071369737386703</MDI>
      <MDI key="STATISTICS_STDDEV">1.#SNAN</MDI>
    </Metadata>
  </PAMRasterBand>
  <PAMRasterBand band="126">
    <Metadata>
      <MDI key="STATISTICS_MAXIMUM">0.11396258324385</MDI>
      <MDI key="STATISTICS_MEAN">1.#SNAN</MDI>
      <MDI key="STATISTICS_MINIMUM">0.069104544818401</MDI>
      <MDI key="STATISTICS_STDDEV">1.#SNAN</MDI>
    </Metadata>
  </PAMRasterBand>
  <PAMRasterBand band="127">
    <Metadata>
      <MDI key="STATISTICS_MAXIMUM">0.11923578381538</MDI>
      <MDI key="STATISTICS_MEAN">1.#SNAN</MDI>
      <MDI key="STATISTICS_MINIMUM">0.072009727358818</MDI>
      <MDI key="STATISTICS_STDDEV">1.#SNAN</MDI>
    </Metadata>
  </PAMRasterBand>
  <PAMRasterBand band="128">
    <Metadata>
      <MDI key="STATISTICS_MAXIMUM">0.11606135219336</MDI>
      <MDI key="STATISTICS_MEAN">1.#SNAN</MDI>
      <MDI key="STATISTICS_MINIMUM">0.070909239351749</MDI>
      <MDI key="STATISTICS_STDDEV">1.#SNAN</MDI>
    </Metadata>
  </PAMRasterBand>
  <PAMRasterBand band="129">
    <Metadata>
      <MDI key="STATISTICS_MAXIMUM">0.1183280646801</MDI>
      <MDI key="STATISTICS_MEAN">1.#SNAN</MDI>
      <MDI key="STATISTICS_MINIMUM">0.06876914203167</MDI>
      <MDI key="STATISTICS_STDDEV">1.#SNAN</MDI>
    </Metadata>
  </PAMRasterBand>
  <PAMRasterBand band="130">
    <Metadata>
      <MDI key="STATISTICS_MAXIMUM">0.11460922658443</MDI>
      <MDI key="STATISTICS_MEAN">1.#SNAN</MDI>
      <MDI key="STATISTICS_MINIMUM">0.067403674125671</MDI>
      <MDI key="STATISTICS_STDDEV">1.#SNAN</MDI>
    </Metadata>
  </PAMRasterBand>
  <PAMRasterBand band="131">
    <Metadata>
      <MDI key="STATISTICS_MAXIMUM">0.1130401417613</MDI>
      <MDI key="STATISTICS_MEAN">1.#SNAN</MDI>
      <MDI key="STATISTICS_MINIMUM">0.066669844090939</MDI>
      <MDI key="STATISTICS_STDDEV">1.#SNAN</MDI>
    </Metadata>
  </PAMRasterBand>
  <PAMRasterBand band="132">
    <Metadata>
      <MDI key="STATISTICS_MAXIMUM">0.10824467986822</MDI>
      <MDI key="STATISTICS_MEAN">1.#SNAN</MDI>
      <MDI key="STATISTICS_MINIMUM">0.063551977276802</MDI>
      <MDI key="STATISTICS_STDDEV">1.#SNAN</MDI>
    </Metadata>
  </PAMRasterBand>
  <PAMRasterBand band="133">
    <Metadata>
      <MDI key="STATISTICS_MAXIMUM">0.1059295758605</MDI>
      <MDI key="STATISTICS_MEAN">1.#SNAN</MDI>
      <MDI key="STATISTICS_MINIMUM">0.056471761316061</MDI>
      <MDI key="STATISTICS_STDDEV">1.#SNAN</MDI>
    </Metadata>
  </PAMRasterBand>
  <PAMRasterBand band="134">
    <Metadata>
      <MDI key="STATISTICS_MAXIMUM">0.10437676310539</MDI>
      <MDI key="STATISTICS_MEAN">1.#SNAN</MDI>
      <MDI key="STATISTICS_MINIMUM">0.058800794184208</MDI>
      <MDI key="STATISTICS_STDDEV">1.#SNAN</MDI>
    </Metadata>
  </PAMRasterBand>
  <PAMRasterBand band="135">
    <Metadata>
      <MDI key="STATISTICS_MAXIMUM">0.095675081014633</MDI>
      <MDI key="STATISTICS_MEAN">1.#SNAN</MDI>
      <MDI key="STATISTICS_MINIMUM">0.055631276220083</MDI>
      <MDI key="STATISTICS_STDDEV">1.#SNAN</MDI>
    </Metadata>
  </PAMRasterBand>
  <PAMRasterBand band="136">
    <Metadata>
      <MDI key="STATISTICS_MAXIMUM">0.096776574850082</MDI>
      <MDI key="STATISTICS_MEAN">1.#SNAN</MDI>
      <MDI key="STATISTICS_MINIMUM">0.052593506872654</MDI>
      <MDI key="STATISTICS_STDDEV">1.#SNAN</MDI>
    </Metadata>
  </PAMRasterBand>
  <PAMRasterBand band="137">
    <Metadata>
      <MDI key="STATISTICS_MAXIMUM">0.09019198268652</MDI>
      <MDI key="STATISTICS_MEAN">1.#SNAN</MDI>
      <MDI key="STATISTICS_MINIMUM">0.047571931034327</MDI>
      <MDI key="STATISTICS_STDDEV">1.#SNAN</MDI>
    </Metadata>
  </PAMRasterBand>
  <PAMRasterBand band="138">
    <Metadata>
      <MDI key="STATISTICS_MAXIMUM">0.088462688028812</MDI>
      <MDI key="STATISTICS_MEAN">1.#SNAN</MDI>
      <MDI key="STATISTICS_MINIMUM">0.044545970857143</MDI>
      <MDI key="STATISTICS_STDDEV">1.#SNAN</MDI>
    </Metadata>
  </PAMRasterBand>
  <PAMRasterBand band="139">
    <Metadata>
      <MDI key="STATISTICS_MAXIMUM">0.087468259036541</MDI>
      <MDI key="STATISTICS_MEAN">1.#SNAN</MDI>
      <MDI key="STATISTICS_MINIMUM">0.042507771402597</MDI>
      <MDI key="STATISTICS_STDDEV">1.#SNAN</MDI>
    </Metadata>
  </PAMRasterBand>
  <PAMRasterBand band="140">
    <Metadata>
      <MDI key="STATISTICS_MAXIMUM">0.084378644824028</MDI>
      <MDI key="STATISTICS_MEAN">1.#SNAN</MDI>
      <MDI key="STATISTICS_MINIMUM">0.044484924525023</MDI>
      <MDI key="STATISTICS_STDDEV">1.#SNAN</MDI>
    </Metadata>
  </PAMRasterBand>
  <PAMRasterBand band="141">
    <Metadata>
      <MDI key="STATISTICS_MAXIMUM">0.082679867744446</MDI>
      <MDI key="STATISTICS_MEAN">1.#SNAN</MDI>
      <MDI key="STATISTICS_MINIMUM">0.041784185916185</MDI>
      <MDI key="STATISTICS_STDDEV">1.#SNAN</MDI>
    </Metadata>
  </PAMRasterBand>
  <PAMRasterBand band="142">
    <Metadata>
      <MDI key="STATISTICS_MAXIMUM">0.080969087779522</MDI>
      <MDI key="STATISTICS_MEAN">1.#SNAN</MDI>
      <MDI key="STATISTICS_MINIMUM">0.037661004811525</MDI>
      <MDI key="STATISTICS_STDDEV">1.#SNAN</MDI>
    </Metadata>
  </PAMRasterBand>
  <PAMRasterBand band="143">
    <Metadata>
      <MDI key="STATISTICS_MAXIMUM">0.071650914847851</MDI>
      <MDI key="STATISTICS_MEAN">1.#SNAN</MDI>
      <MDI key="STATISTICS_MINIMUM">0.03683278337121</MDI>
      <MDI key="STATISTICS_STDDEV">1.#SNAN</MDI>
    </Metadata>
  </PAMRasterBand>
  <PAMRasterBand band="144">
    <Metadata>
      <MDI key="STATISTICS_MAXIMUM">0.071670077741146</MDI>
      <MDI key="STATISTICS_MEAN">1.#SNAN</MDI>
      <MDI key="STATISTICS_MINIMUM">0.032853461802006</MDI>
      <MDI key="STATISTICS_STDDEV">1.#SNAN</MDI>
    </Metadata>
  </PAMRasterBand>
  <PAMRasterBand band="145">
    <Metadata>
      <MDI key="STATISTICS_MAXIMUM">0.066008858382702</MDI>
      <MDI key="STATISTICS_MEAN">1.#SNAN</MDI>
      <MDI key="STATISTICS_MINIMUM">0.032150458544493</MDI>
      <MDI key="STATISTICS_STDDEV">1.#SNAN</MDI>
    </Metadata>
  </PAMRasterBand>
  <PAMRasterBand band="146">
    <Metadata>
      <MDI key="STATISTICS_MAXIMUM">0.064608372747898</MDI>
      <MDI key="STATISTICS_MEAN">1.#SNAN</MDI>
      <MDI key="STATISTICS_MINIMUM">0.029336160048842</MDI>
      <MDI key="STATISTICS_STDDEV">1.#SNAN</MDI>
    </Metadata>
  </PAMRasterBand>
  <PAMRasterBand band="147">
    <Metadata>
      <MDI key="STATISTICS_MAXIMUM">0.059715673327446</MDI>
      <MDI key="STATISTICS_MEAN">1.#SNAN</MDI>
      <MDI key="STATISTICS_MINIMUM">0.029194314032793</MDI>
      <MDI key="STATISTICS_STDDEV">1.#SNAN</MDI>
    </Metadata>
  </PAMRasterBand>
  <PAMRasterBand band="148">
    <Metadata>
      <MDI key="STATISTICS_MAXIMUM">0.06304557621479</MDI>
      <MDI key="STATISTICS_MEAN">1.#SNAN</MDI>
      <MDI key="STATISTICS_MINIMUM">0.026245057582855</MDI>
      <MDI key="STATISTICS_STDDEV">1.#SNAN</MDI>
    </Metadata>
  </PAMRasterBand>
  <PAMRasterBand band="149">
    <Metadata>
      <MDI key="STATISTICS_MAXIMUM">0.058035027235746</MDI>
      <MDI key="STATISTICS_MEAN">1.#SNAN</MDI>
      <MDI key="STATISTICS_MINIMUM">0.023337177932262</MDI>
      <MDI key="STATISTICS_STDDEV">1.#SNAN</MDI>
    </Metadata>
  </PAMRasterBand>
  <PAMRasterBand band="150">
    <Metadata>
      <MDI key="STATISTICS_MAXIMUM">0.058676216751337</MDI>
      <MDI key="STATISTICS_MEAN">1.#SNAN</MDI>
      <MDI key="STATISTICS_MINIMUM">0.021672636270523</MDI>
      <MDI key="STATISTICS_STDDEV">1.#SNAN</MDI>
    </Metadata>
  </PAMRasterBand>
  <PAMRasterBand band="151">
    <Metadata>
      <MDI key="STATISTICS_MAXIMUM">0.058268528431654</MDI>
      <MDI key="STATISTICS_MEAN">1.#SNAN</MDI>
      <MDI key="STATISTICS_MINIMUM">0.023237375542521</MDI>
      <MDI key="STATISTICS_STDDEV">1.#SNAN</MDI>
    </Metadata>
  </PAMRasterBand>
  <PAMRasterBand band="152">
    <Metadata>
      <MDI key="STATISTICS_MAXIMUM">0.058952949941158</MDI>
      <MDI key="STATISTICS_MEAN">1.#SNAN</MDI>
      <MDI key="STATISTICS_MINIMUM">0.022716507315636</MDI>
      <MDI key="STATISTICS_STDDEV">1.#SNAN</MDI>
    </Metadata>
  </PAMRasterBand>
  <PAMRasterBand band="153">
    <Metadata>
      <MDI key="STATISTICS_MAXIMUM">0.057751532644033</MDI>
      <MDI key="STATISTICS_MEAN">1.#SNAN</MDI>
      <MDI key="STATISTICS_MINIMUM">0.023993479087949</MDI>
      <MDI key="STATISTICS_STDDEV">1.#SNAN</MDI>
    </Metadata>
  </PAMRasterBand>
  <PAMRasterBand band="154">
    <Metadata>
      <MDI key="STATISTICS_MAXIMUM">0.055917482823133</MDI>
      <MDI key="STATISTICS_MEAN">1.#SNAN</MDI>
      <MDI key="STATISTICS_MINIMUM">0.023269142955542</MDI>
      <MDI key="STATISTICS_STDDEV">1.#SNAN</MDI>
    </Metadata>
  </PAMRasterBand>
  <PAMRasterBand band="155">
    <Metadata>
      <MDI key="STATISTICS_MAXIMUM">0.058843657374382</MDI>
      <MDI key="STATISTICS_MEAN">1.#SNAN</MDI>
      <MDI key="STATISTICS_MINIMUM">0.024099208414555</MDI>
      <MDI key="STATISTICS_STDDEV">1.#SNAN</MDI>
    </Metadata>
  </PAMRasterBand>
  <PAMRasterBand band="156">
    <Metadata>
      <MDI key="STATISTICS_MAXIMUM">0.064028404653072</MDI>
      <MDI key="STATISTICS_MEAN">1.#SNAN</MDI>
      <MDI key="STATISTICS_MINIMUM">0.028102455660701</MDI>
      <MDI key="STATISTICS_STDDEV">1.#SNAN</MDI>
    </Metadata>
  </PAMRasterBand>
  <PAMRasterBand band="157">
    <Metadata>
      <MDI key="STATISTICS_MAXIMUM">0.070512101054192</MDI>
      <MDI key="STATISTICS_MEAN">1.#SNAN</MDI>
      <MDI key="STATISTICS_MINIMUM">0.031349714845419</MDI>
      <MDI key="STATISTICS_STDDEV">1.#SNAN</MDI>
    </Metadata>
  </PAMRasterBand>
  <PAMRasterBand band="158">
    <Metadata>
      <MDI key="STATISTICS_MAXIMUM">0.077447384595871</MDI>
      <MDI key="STATISTICS_MEAN">1.#SNAN</MDI>
      <MDI key="STATISTICS_MINIMUM">0.037269227206707</MDI>
      <MDI key="STATISTICS_STDDEV">1.#SNAN</MDI>
    </Metadata>
  </PAMRasterBand>
  <PAMRasterBand band="159">
    <Metadata>
      <MDI key="STATISTICS_MAXIMUM">0.098119087517262</MDI>
      <MDI key="STATISTICS_MEAN">1.#SNAN</MDI>
      <MDI key="STATISTICS_MINIMUM">0.045805428177118</MDI>
      <MDI key="STATISTICS_STDDEV">1.#SNAN</MDI>
    </Metadata>
  </PAMRasterBand>
  <PAMRasterBand band="160">
    <Metadata>
      <MDI key="STATISTICS_MAXIMUM">0.10790904611349</MDI>
      <MDI key="STATISTICS_MEAN">1.#SNAN</MDI>
      <MDI key="STATISTICS_MINIMUM">0.058714915066957</MDI>
      <MDI key="STATISTICS_STDDEV">1.#SNAN</MDI>
    </Metadata>
  </PAMRasterBand>
  <PAMRasterBand band="161">
    <Metadata>
      <MDI key="STATISTICS_MAXIMUM">0.1290967464447</MDI>
      <MDI key="STATISTICS_MEAN">1.#SNAN</MDI>
      <MDI key="STATISTICS_MINIMUM">0.064597405493259</MDI>
      <MDI key="STATISTICS_STDDEV">1.#SNAN</MDI>
    </Metadata>
  </PAMRasterBand>
  <PAMRasterBand band="162">
    <Metadata>
      <MDI key="STATISTICS_MAXIMUM">0.14486412703991</MDI>
      <MDI key="STATISTICS_MEAN">1.#SNAN</MDI>
      <MDI key="STATISTICS_MINIMUM">0.091156676411629</MDI>
      <MDI key="STATISTICS_STDDEV">1.#SNAN</MDI>
    </Metadata>
  </PAMRasterBand>
  <PAMRasterBand band="163">
    <Metadata>
      <MDI key="STATISTICS_MAXIMUM">0.16876973211765</MDI>
      <MDI key="STATISTICS_MEAN">1.#SNAN</MDI>
      <MDI key="STATISTICS_MINIMUM">0.10630282759666</MDI>
      <MDI key="STATISTICS_STDDEV">1.#SNAN</MDI>
    </Metadata>
  </PAMRasterBand>
  <PAMRasterBand band="164">
    <Metadata>
      <MDI key="STATISTICS_MAXIMUM">0.19748447835445</MDI>
      <MDI key="STATISTICS_MEAN">1.#SNAN</MDI>
      <MDI key="STATISTICS_MINIMUM">0.12819720804691</MDI>
      <MDI key="STATISTICS_STDDEV">1.#SNAN</MDI>
    </Metadata>
  </PAMRasterBand>
  <PAMRasterBand band="165">
    <Metadata>
      <MDI key="STATISTICS_MAXIMUM">0.22440676391125</MDI>
      <MDI key="STATISTICS_MEAN">1.#SNAN</MDI>
      <MDI key="STATISTICS_MINIMUM">0.14788334071636</MDI>
      <MDI key="STATISTICS_STDDEV">1.#SNAN</MDI>
    </Metadata>
  </PAMRasterBand>
  <PAMRasterBand band="166">
    <Metadata>
      <MDI key="STATISTICS_MAXIMUM">0.25375187397003</MDI>
      <MDI key="STATISTICS_MEAN">1.#SNAN</MDI>
      <MDI key="STATISTICS_MINIMUM">0.16145664453506</MDI>
      <MDI key="STATISTICS_STDDEV">1.#SNAN</MDI>
    </Metadata>
  </PAMRasterBand>
  <PAMRasterBand band="167">
    <Metadata>
      <MDI key="STATISTICS_MAXIMUM">0.28467392921448</MDI>
      <MDI key="STATISTICS_MEAN">1.#SNAN</MDI>
      <MDI key="STATISTICS_MINIMUM">0.19873483479023</MDI>
      <MDI key="STATISTICS_STDDEV">1.#SNAN</MDI>
    </Metadata>
  </PAMRasterBand>
  <PAMRasterBand band="168">
    <Metadata>
      <MDI key="STATISTICS_MAXIMUM">0.31562379002571</MDI>
      <MDI key="STATISTICS_MEAN">1.#SNAN</MDI>
      <MDI key="STATISTICS_MINIMUM">0.22454792261124</MDI>
      <MDI key="STATISTICS_STDDEV">1.#SNAN</MDI>
    </Metadata>
  </PAMRasterBand>
  <PAMRasterBand band="169">
    <Metadata>
      <MDI key="STATISTICS_MAXIMUM">0.33331003785133</MDI>
      <MDI key="STATISTICS_MEAN">1.#SNAN</MDI>
      <MDI key="STATISTICS_MINIMUM">0.2383069396019</MDI>
      <MDI key="STATISTICS_STDDEV">1.#SNAN</MDI>
    </Metadata>
  </PAMRasterBand>
  <PAMRasterBand band="170">
    <Metadata>
      <MDI key="STATISTICS_MAXIMUM">0.36622950434685</MDI>
      <MDI key="STATISTICS_MEAN">1.#SNAN</MDI>
      <MDI key="STATISTICS_MINIMUM">0.27489003539085</MDI>
      <MDI key="STATISTICS_STDDEV">1.#SNAN</MDI>
    </Metadata>
  </PAMRasterBand>
  <PAMRasterBand band="171">
    <Metadata>
      <MDI key="STATISTICS_MAXIMUM">0.39515048265457</MDI>
      <MDI key="STATISTICS_MEAN">1.#SNAN</MDI>
      <MDI key="STATISTICS_MINIMUM">0.2963573038578</MDI>
      <MDI key="STATISTICS_STDDEV">1.#SNAN</MDI>
    </Metadata>
  </PAMRasterBand>
  <PAMRasterBand band="172">
    <Metadata>
      <MDI key="STATISTICS_MAXIMUM">0.43650344014168</MDI>
      <MDI key="STATISTICS_MEAN">1.#SNAN</MDI>
      <MDI key="STATISTICS_MINIMUM">0.32141050696373</MDI>
      <MDI key="STATISTICS_STDDEV">1.#SNAN</MDI>
    </Metadata>
  </PAMRasterBand>
  <PAMRasterBand band="173">
    <Metadata>
      <MDI key="STATISTICS_MAXIMUM">0.46053138375282</MDI>
      <MDI key="STATISTICS_MEAN">1.#SNAN</MDI>
      <MDI key="STATISTICS_MINIMUM">0.34677523374557</MDI>
      <MDI key="STATISTICS_STDDEV">1.#SNAN</MDI>
    </Metadata>
  </PAMRasterBand>
  <PAMRasterBand band="174">
    <Metadata>
      <MDI key="STATISTICS_MAXIMUM">0.49360078573227</MDI>
      <MDI key="STATISTICS_MEAN">1.#SNAN</MDI>
      <MDI key="STATISTICS_MINIMUM">0.37554731965065</MDI>
      <MDI key="STATISTICS_STDDEV">1.#SNAN</MDI>
    </Metadata>
  </PAMRasterBand>
  <PAMRasterBand band="175">
    <Metadata>
      <MDI key="STATISTICS_MAXIMUM">0.52118158340454</MDI>
      <MDI key="STATISTICS_MEAN">1.#SNAN</MDI>
      <MDI key="STATISTICS_MINIMUM">0.39599028229713</MDI>
      <MDI key="STATISTICS_STDDEV">1.#SNAN</MDI>
    </Metadata>
  </PAMRasterBand>
  <PAMRasterBand band="176">
    <Metadata>
      <MDI key="STATISTICS_MAXIMUM">0.5637035369873</MDI>
      <MDI key="STATISTICS_MEAN">1.#SNAN</MDI>
      <MDI key="STATISTICS_MINIMUM">0.42229655385017</MDI>
      <MDI key="STATISTICS_STDDEV">1.#SNAN</MDI>
    </Metadata>
  </PAMRasterBand>
  <PAMRasterBand band="177">
    <Metadata>
      <MDI key="STATISTICS_MAXIMUM">0.56675213575363</MDI>
      <MDI key="STATISTICS_MEAN">1.#SNAN</MDI>
      <MDI key="STATISTICS_MINIMUM">0.43902918696404</MDI>
      <MDI key="STATISTICS_STDDEV">1.#SNAN</MDI>
    </Metadata>
  </PAMRasterBand>
  <PAMRasterBand band="178">
    <Metadata>
      <MDI key="STATISTICS_MAXIMUM">0.61279296875</MDI>
      <MDI key="STATISTICS_MEAN">1.#SNAN</MDI>
      <MDI key="STATISTICS_MINIMUM">0.48125037550926</MDI>
      <MDI key="STATISTICS_STDDEV">1.#SNAN</MDI>
    </Metadata>
  </PAMRasterBand>
  <PAMRasterBand band="179">
    <Metadata>
      <MDI key="STATISTICS_MAXIMUM">0.61814546585083</MDI>
      <MDI key="STATISTICS_MEAN">1.#SNAN</MDI>
      <MDI key="STATISTICS_MINIMUM">0.49977535009384</MDI>
      <MDI key="STATISTICS_STDDEV">1.#SNAN</MDI>
    </Metadata>
  </PAMRasterBand>
  <PAMRasterBand band="180">
    <Metadata>
      <MDI key="STATISTICS_MAXIMUM">0.65539389848709</MDI>
      <MDI key="STATISTICS_MEAN">1.#SNAN</MDI>
      <MDI key="STATISTICS_MINIMUM">0.5125789642334</MDI>
      <MDI key="STATISTICS_STDDEV">1.#SNAN</MDI>
    </Metadata>
  </PAMRasterBand>
  <PAMRasterBand band="181">
    <Metadata>
      <MDI key="STATISTICS_MAXIMUM">0.69052904844284</MDI>
      <MDI key="STATISTICS_MEAN">1.#SNAN</MDI>
      <MDI key="STATISTICS_MINIMUM">0.53780627250671</MDI>
      <MDI key="STATISTICS_STDDEV">1.#SNAN</MDI>
    </Metadata>
  </PAMRasterBand>
  <PAMRasterBand band="182">
    <Metadata>
      <MDI key="STATISTICS_MAXIMUM">0.69937086105347</MDI>
      <MDI key="STATISTICS_MEAN">1.#SNAN</MDI>
      <MDI key="STATISTICS_MINIMUM">0.56627231836319</MDI>
      <MDI key="STATISTICS_STDDEV">1.#SNAN</MDI>
    </Metadata>
  </PAMRasterBand>
  <PAMRasterBand band="183">
    <Metadata>
      <MDI key="STATISTICS_MAXIMUM">0.73322904109955</MDI>
      <MDI key="STATISTICS_MEAN">1.#SNAN</MDI>
      <MDI key="STATISTICS_MINIMUM">0.59490531682968</MDI>
      <MDI key="STATISTICS_STDDEV">1.#SNAN</MDI>
    </Metadata>
  </PAMRasterBand>
  <PAMRasterBand band="184">
    <Metadata>
      <MDI key="STATISTICS_MAXIMUM">0.73352926969528</MDI>
      <MDI key="STATISTICS_MEAN">1.#SNAN</MDI>
      <MDI key="STATISTICS_MINIMUM">0.60198265314102</MDI>
      <MDI key="STATISTICS_STDDEV">1.#SNAN</MDI>
    </Metadata>
  </PAMRasterBand>
  <PAMRasterBand band="185">
    <Metadata>
      <MDI key="STATISTICS_MAXIMUM">0.7409560084343</MDI>
      <MDI key="STATISTICS_MEAN">1.#SNAN</MDI>
      <MDI key="STATISTICS_MINIMUM">0.60959440469742</MDI>
      <MDI key="STATISTICS_STDDEV">1.#SNAN</MDI>
    </Metadata>
  </PAMRasterBand>
  <PAMRasterBand band="186">
    <Metadata>
      <MDI key="STATISTICS_MAXIMUM">0.77617251873016</MDI>
      <MDI key="STATISTICS_MEAN">1.#SNAN</MDI>
      <MDI key="STATISTICS_MINIMUM">0.6304115653038</MDI>
      <MDI key="STATISTICS_STDDEV">1.#SNAN</MDI>
    </Metadata>
  </PAMRasterBand>
  <PAMRasterBand band="187">
    <Metadata>
      <MDI key="STATISTICS_MAXIMUM">0.81615501642227</MDI>
      <MDI key="STATISTICS_MEAN">1.#SNAN</MDI>
      <MDI key="STATISTICS_MINIMUM">0.64064866304398</MDI>
      <MDI key="STATISTICS_STDDEV">1.#SNAN</MDI>
    </Metadata>
  </PAMRasterBand>
  <PAMRasterBand band="188">
    <Metadata>
      <MDI key="STATISTICS_MAXIMUM">0.79272603988647</MDI>
      <MDI key="STATISTICS_MEAN">1.#SNAN</MDI>
      <MDI key="STATISTICS_MINIMUM">0.65197604894638</MDI>
      <MDI key="STATISTICS_STDDEV">1.#SNAN</MDI>
    </Metadata>
  </PAMRasterBand>
  <PAMRasterBand band="189">
    <Metadata>
      <MDI key="STATISTICS_MAXIMUM">0.8089656829834</MDI>
      <MDI key="STATISTICS_MEAN">1.#SNAN</MDI>
      <MDI key="STATISTICS_MINIMUM">0.64569789171219</MDI>
      <MDI key="STATISTICS_STDDEV">1.#SNAN</MDI>
    </Metadata>
  </PAMRasterBand>
  <PAMRasterBand band="190">
    <Metadata>
      <MDI key="STATISTICS_MAXIMUM">0.82875382900238</MDI>
      <MDI key="STATISTICS_MEAN">1.#SNAN</MDI>
      <MDI key="STATISTICS_MINIMUM">0.65840417146683</MDI>
      <MDI key="STATISTICS_STDDEV">1.#SNAN</MDI>
    </Metadata>
  </PAMRasterBand>
  <PAMRasterBand band="191">
    <Metadata>
      <MDI key="STATISTICS_MAXIMUM">0.84918564558029</MDI>
      <MDI key="STATISTICS_MEAN">1.#SNAN</MDI>
      <MDI key="STATISTICS_MINIMUM">0.68203055858612</MDI>
      <MDI key="STATISTICS_STDDEV">1.#SNAN</MDI>
    </Metadata>
  </PAMRasterBand>
  <PAMRasterBand band="192">
    <Metadata>
      <MDI key="STATISTICS_MAXIMUM">0.84819084405899</MDI>
      <MDI key="STATISTICS_MEAN">1.#SNAN</MDI>
      <MDI key="STATISTICS_MINIMUM">0.67655700445175</MDI>
      <MDI key="STATISTICS_STDDEV">1.#SNAN</MDI>
    </Metadata>
  </PAMRasterBand>
  <PAMRasterBand band="193">
    <Metadata>
      <MDI key="STATISTICS_MAXIMUM">0.85818827152252</MDI>
      <MDI key="STATISTICS_MEAN">1.#SNAN</MDI>
      <MDI key="STATISTICS_MINIMUM">0.68213188648224</MDI>
      <MDI key="STATISTICS_STDDEV">1.#SNAN</MDI>
    </Metadata>
  </PAMRasterBand>
  <PAMRasterBand band="194">
    <Metadata>
      <MDI key="STATISTICS_MAXIMUM">0.8711970448494</MDI>
      <MDI key="STATISTICS_MEAN">1.#SNAN</MDI>
      <MDI key="STATISTICS_MINIMUM">0.67957502603531</MDI>
      <MDI key="STATISTICS_STDDEV">1.#SNAN</MDI>
    </Metadata>
  </PAMRasterBand>
  <PAMRasterBand band="195">
    <Metadata>
      <MDI key="STATISTICS_MAXIMUM">0.87209790945053</MDI>
      <MDI key="STATISTICS_MEAN">1.#SNAN</MDI>
      <MDI key="STATISTICS_MINIMUM">0.70350068807602</MDI>
      <MDI key="STATISTICS_STDDEV">1.#SNAN</MDI>
    </Metadata>
  </PAMRasterBand>
  <PAMRasterBand band="196">
    <Metadata>
      <MDI key="STATISTICS_MAXIMUM">0.91296780109406</MDI>
      <MDI key="STATISTICS_MEAN">1.#SNAN</MDI>
      <MDI key="STATISTICS_MINIMUM">0.70256292819977</MDI>
      <MDI key="STATISTICS_STDDEV">1.#SNAN</MDI>
    </Metadata>
  </PAMRasterBand>
  <PAMRasterBand band="197">
    <Metadata>
      <MDI key="STATISTICS_MAXIMUM">0.962571144104</MDI>
      <MDI key="STATISTICS_MEAN">1.#SNAN</MDI>
      <MDI key="STATISTICS_MINIMUM">0.75562143325806</MDI>
      <MDI key="STATISTICS_STDDEV">1.#SNAN</MDI>
    </Metadata>
  </PAMRasterBand>
  <PAMRasterBand band="198">
    <Metadata>
      <MDI key="STATISTICS_MAXIMUM">0.91706770658493</MDI>
      <MDI key="STATISTICS_MEAN">1.#SNAN</MDI>
      <MDI key="STATISTICS_MINIMUM">0.66969364881516</MDI>
      <MDI key="STATISTICS_STDDEV">1.#SNAN</MDI>
    </Metadata>
  </PAMRasterBand>
  <PAMRasterBand band="199">
    <Metadata>
      <MDI key="STATISTICS_MAXIMUM">0.85331642627716</MDI>
      <MDI key="STATISTICS_MEAN">1.#SNAN</MDI>
      <MDI key="STATISTICS_MINIMUM">0.65429627895355</MDI>
      <MDI key="STATISTICS_STDDEV">1.#SNAN</MDI>
    </Metadata>
  </PAMRasterBand>
  <PAMRasterBand band="200">
    <Metadata>
      <MDI key="STATISTICS_MAXIMUM">0.91150349378586</MDI>
      <MDI key="STATISTICS_MEAN">1.#SNAN</MDI>
      <MDI key="STATISTICS_MINIMUM">0.68843644857407</MDI>
      <MDI key="STATISTICS_STDDEV">1.#SNAN</MDI>
    </Metadata>
  </PAMRasterBand>
  <PAMRasterBand band="201">
    <Metadata>
      <MDI key="STATISTICS_MAXIMUM">0.88999354839325</MDI>
      <MDI key="STATISTICS_MEAN">1.#SNAN</MDI>
      <MDI key="STATISTICS_MINIMUM">0.67022681236267</MDI>
      <MDI key="STATISTICS_STDDEV">1.#SNAN</MDI>
    </Metadata>
  </PAMRasterBand>
  <PAMRasterBand band="202">
    <Metadata>
      <MDI key="STATISTICS_MAXIMUM">0.88598889112473</MDI>
      <MDI key="STATISTICS_MEAN">1.#SNAN</MDI>
      <MDI key="STATISTICS_MINIMUM">0.70078539848328</MDI>
      <MDI key="STATISTICS_STDDEV">1.#SNAN</MDI>
    </Metadata>
  </PAMRasterBand>
  <PAMRasterBand band="203">
    <Metadata>
      <MDI key="STATISTICS_MAXIMUM">0.90554291009903</MDI>
      <MDI key="STATISTICS_MEAN">1.#SNAN</MDI>
      <MDI key="STATISTICS_MINIMUM">0.70565235614777</MDI>
      <MDI key="STATISTICS_STDDEV">1.#SNAN</MDI>
    </Metadata>
  </PAMRasterBand>
  <PAMRasterBand band="204">
    <Metadata>
      <MDI key="STATISTICS_MAXIMUM">0.89239144325256</MDI>
      <MDI key="STATISTICS_MEAN">1.#SNAN</MDI>
      <MDI key="STATISTICS_MINIMUM">0.69412803649902</MDI>
      <MDI key="STATISTICS_STDDEV">1.#SNAN</MDI>
    </Metadata>
  </PAMRasterBand>
  <PAMRasterBand band="205">
    <Metadata>
      <MDI key="STATISTICS_MAXIMUM">0.89521771669388</MDI>
      <MDI key="STATISTICS_MEAN">1.#SNAN</MDI>
      <MDI key="STATISTICS_MINIMUM">0.70623511075974</MDI>
      <MDI key="STATISTICS_STDDEV">1.#SNAN</MDI>
    </Metadata>
  </PAMRasterBand>
  <PAMRasterBand band="206">
    <Metadata>
      <MDI key="STATISTICS_MAXIMUM">0.88758128881454</MDI>
      <MDI key="STATISTICS_MEAN">1.#SNAN</MDI>
      <MDI key="STATISTICS_MINIMUM">0.69504523277283</MDI>
      <MDI key="STATISTICS_STDDEV">1.#SNAN</MDI>
    </Metadata>
  </PAMRasterBand>
  <PAMRasterBand band="207">
    <Metadata>
      <MDI key="STATISTICS_MAXIMUM">0.90371245145798</MDI>
      <MDI key="STATISTICS_MEAN">1.#SNAN</MDI>
      <MDI key="STATISTICS_MINIMUM">0.69951719045639</MDI>
      <MDI key="STATISTICS_STDDEV">1.#SNAN</MDI>
    </Metadata>
  </PAMRasterBand>
  <PAMRasterBand band="208">
    <Metadata>
      <MDI key="STATISTICS_MAXIMUM">0.89431697130203</MDI>
      <MDI key="STATISTICS_MEAN">1.#SNAN</MDI>
      <MDI key="STATISTICS_MINIMUM">0.7182332277298</MDI>
      <MDI key="STATISTICS_STDDEV">1.#SNAN</MDI>
    </Metadata>
  </PAMRasterBand>
  <PAMRasterBand band="209">
    <Metadata>
      <MDI key="STATISTICS_MAXIMUM">0.92534595727921</MDI>
      <MDI key="STATISTICS_MEAN">1.#SNAN</MDI>
      <MDI key="STATISTICS_MINIMUM">0.72149688005447</MDI>
      <MDI key="STATISTICS_STDDEV">1.#SNAN</MDI>
    </Metadata>
  </PAMRasterBand>
  <PAMRasterBand band="210">
    <Metadata>
      <MDI key="STATISTICS_MAXIMUM">0.9008926153183</MDI>
      <MDI key="STATISTICS_MEAN">1.#SNAN</MDI>
      <MDI key="STATISTICS_MINIMUM">0.71124535799026</MDI>
      <MDI key="STATISTICS_STDDEV">1.#SNAN</MDI>
    </Metadata>
  </PAMRasterBand>
  <PAMRasterBand band="211">
    <Metadata>
      <MDI key="STATISTICS_MAXIMUM">0.91788810491562</MDI>
      <MDI key="STATISTICS_MEAN">1.#SNAN</MDI>
      <MDI key="STATISTICS_MINIMUM">0.73025685548782</MDI>
      <MDI key="STATISTICS_STDDEV">1.#SNAN</MDI>
    </Metadata>
  </PAMRasterBand>
  <PAMRasterBand band="212">
    <Metadata>
      <MDI key="STATISTICS_MAXIMUM">0.91735935211182</MDI>
      <MDI key="STATISTICS_MEAN">1.#SNAN</MDI>
      <MDI key="STATISTICS_MINIMUM">0.72896820306778</MDI>
      <MDI key="STATISTICS_STDDEV">1.#SNAN</MDI>
    </Metadata>
  </PAMRasterBand>
  <PAMRasterBand band="213">
    <Metadata>
      <MDI key="STATISTICS_MAXIMUM">0.91601598262787</MDI>
      <MDI key="STATISTICS_MEAN">1.#SNAN</MDI>
      <MDI key="STATISTICS_MINIMUM">0.71848464012146</MDI>
      <MDI key="STATISTICS_STDDEV">1.#SNAN</MDI>
    </Metadata>
  </PAMRasterBand>
  <PAMRasterBand band="214">
    <Metadata>
      <MDI key="STATISTICS_MAXIMUM">0.92105025053024</MDI>
      <MDI key="STATISTICS_MEAN">1.#SNAN</MDI>
      <MDI key="STATISTICS_MINIMUM">0.71568089723587</MDI>
      <MDI key="STATISTICS_STDDEV">1.#SNAN</MDI>
    </Metadata>
  </PAMRasterBand>
  <PAMRasterBand band="215">
    <Metadata>
      <MDI key="STATISTICS_MAXIMUM">0.86051386594772</MDI>
      <MDI key="STATISTICS_MEAN">1.#SNAN</MDI>
      <MDI key="STATISTICS_MINIMUM">0.68038928508759</MDI>
      <MDI key="STATISTICS_STDDEV">1.#SNAN</MDI>
    </Metadata>
  </PAMRasterBand>
  <PAMRasterBand band="216">
    <Metadata>
      <MDI key="STATISTICS_MAXIMUM">0.89878165721893</MDI>
      <MDI key="STATISTICS_MEAN">1.#SNAN</MDI>
      <MDI key="STATISTICS_MINIMUM">0.69169509410858</MDI>
      <MDI key="STATISTICS_STDDEV">1.#SNAN</MDI>
    </Metadata>
  </PAMRasterBand>
  <PAMRasterBand band="217">
    <Metadata>
      <MDI key="STATISTICS_MAXIMUM">0.89742177724838</MDI>
      <MDI key="STATISTICS_MEAN">1.#SNAN</MDI>
      <MDI key="STATISTICS_MINIMUM">0.69604337215424</MDI>
      <MDI key="STATISTICS_STDDEV">1.#SNAN</MDI>
    </Metadata>
  </PAMRasterBand>
  <PAMRasterBand band="218">
    <Metadata>
      <MDI key="STATISTICS_MAXIMUM">0.94927757978439</MDI>
      <MDI key="STATISTICS_MEAN">1.#SNAN</MDI>
      <MDI key="STATISTICS_MINIMUM">0.73737281560898</MDI>
      <MDI key="STATISTICS_STDDEV">1.#SNAN</MDI>
    </Metadata>
  </PAMRasterBand>
  <PAMRasterBand band="219">
    <Metadata>
      <MDI key="STATISTICS_MAXIMUM">0.90081721544266</MDI>
      <MDI key="STATISTICS_MEAN">1.#SNAN</MDI>
      <MDI key="STATISTICS_MINIMUM">0.70349311828613</MDI>
      <MDI key="STATISTICS_STDDEV">1.#SNAN</MDI>
    </Metadata>
  </PAMRasterBand>
  <PAMRasterBand band="220">
    <Metadata>
      <MDI key="STATISTICS_MAXIMUM">0.91352343559265</MDI>
      <MDI key="STATISTICS_MEAN">1.#SNAN</MDI>
      <MDI key="STATISTICS_MINIMUM">0.71427792310715</MDI>
      <MDI key="STATISTICS_STDDEV">1.#SNAN</MDI>
    </Metadata>
  </PAMRasterBand>
  <PAMRasterBand band="221">
    <Metadata>
      <MDI key="STATISTICS_MAXIMUM">0.9345121383667</MDI>
      <MDI key="STATISTICS_MEAN">1.#SNAN</MDI>
      <MDI key="STATISTICS_MINIMUM">0.72919231653214</MDI>
      <MDI key="STATISTICS_STDDEV">1.#SNAN</MDI>
    </Metadata>
  </PAMRasterBand>
  <PAMRasterBand band="222">
    <Metadata>
      <MDI key="STATISTICS_MAXIMUM">0.94829457998276</MDI>
      <MDI key="STATISTICS_MEAN">1.#SNAN</MDI>
      <MDI key="STATISTICS_MINIMUM">0.75027275085449</MDI>
      <MDI key="STATISTICS_STDDEV">1.#SNAN</MDI>
    </Metadata>
  </PAMRasterBand>
  <PAMRasterBand band="223">
    <Metadata>
      <MDI key="STATISTICS_MAXIMUM">0.92443895339966</MDI>
      <MDI key="STATISTICS_MEAN">1.#SNAN</MDI>
      <MDI key="STATISTICS_MINIMUM">0.7157279253006</MDI>
      <MDI key="STATISTICS_STDDEV">1.#SNAN</MDI>
    </Metadata>
  </PAMRasterBand>
  <PAMRasterBand band="224">
    <Metadata>
      <MDI key="STATISTICS_MAXIMUM">0.92454308271408</MDI>
      <MDI key="STATISTICS_MEAN">1.#SNAN</MDI>
      <MDI key="STATISTICS_MINIMUM">0.70070773363113</MDI>
      <MDI key="STATISTICS_STDDEV">1.#SNAN</MDI>
    </Metadata>
  </PAMRasterBand>
  <PAMRasterBand band="225">
    <Metadata>
      <MDI key="STATISTICS_MAXIMUM">0.89359366893768</MDI>
      <MDI key="STATISTICS_MEAN">1.#SNAN</MDI>
      <MDI key="STATISTICS_MINIMUM">0.67048972845078</MDI>
      <MDI key="STATISTICS_STDDEV">1.#SNAN</MDI>
    </Metadata>
  </PAMRasterBand>
  <PAMRasterBand band="226">
    <Metadata>
      <MDI key="STATISTICS_MAXIMUM">0.9832723736763</MDI>
      <MDI key="STATISTICS_MEAN">1.#SNAN</MDI>
      <MDI key="STATISTICS_MINIMUM">0.75204181671143</MDI>
      <MDI key="STATISTICS_STDDEV">1.#SNAN</MDI>
    </Metadata>
  </PAMRasterBand>
  <PAMRasterBand band="227">
    <Metadata>
      <MDI key="STATISTICS_MAXIMUM">0.9292539358139</MDI>
      <MDI key="STATISTICS_MEAN">1.#SNAN</MDI>
      <MDI key="STATISTICS_MINIMUM">0.69788712263107</MDI>
      <MDI key="STATISTICS_STDDEV">1.#SNAN</MDI>
    </Metadata>
  </PAMRasterBand>
  <PAMRasterBand band="228">
    <Metadata>
      <MDI key="STATISTICS_MAXIMUM">0.99531334638596</MDI>
      <MDI key="STATISTICS_MEAN">1.#SNAN</MDI>
      <MDI key="STATISTICS_MINIMUM">0.74003010988235</MDI>
      <MDI key="STATISTICS_STDDEV">1.#SNAN</MDI>
    </Metadata>
  </PAMRasterBand>
  <PAMRasterBand band="229">
    <Metadata>
      <MDI key="STATISTICS_MAXIMUM">0.90245413780212</MDI>
      <MDI key="STATISTICS_MEAN">1.#SNAN</MDI>
      <MDI key="STATISTICS_MINIMUM">0.64101326465607</MDI>
      <MDI key="STATISTICS_STDDEV">1.#SNAN</MDI>
    </Metadata>
  </PAMRasterBand>
  <PAMRasterBand band="230">
    <Metadata>
      <MDI key="STATISTICS_MAXIMUM">0.89045989513397</MDI>
      <MDI key="STATISTICS_MEAN">1.#SNAN</MDI>
      <MDI key="STATISTICS_MINIMUM">0.66780972480774</MDI>
      <MDI key="STATISTICS_STDDEV">1.#SNAN</MDI>
    </Metadata>
  </PAMRasterBand>
  <PAMRasterBand band="231">
    <Metadata>
      <MDI key="STATISTICS_MAXIMUM">0.91530102491379</MDI>
      <MDI key="STATISTICS_MEAN">1.#SNAN</MDI>
      <MDI key="STATISTICS_MINIMUM">0.69245630502701</MDI>
      <MDI key="STATISTICS_STDDEV">1.#SNAN</MDI>
    </Metadata>
  </PAMRasterBand>
  <PAMRasterBand band="232">
    <Metadata>
      <MDI key="STATISTICS_MAXIMUM">0.95706641674042</MDI>
      <MDI key="STATISTICS_MEAN">1.#SNAN</MDI>
      <MDI key="STATISTICS_MINIMUM">0.69418257474899</MDI>
      <MDI key="STATISTICS_STDDEV">1.#SNAN</MDI>
    </Metadata>
  </PAMRasterBand>
  <PAMRasterBand band="233">
    <Metadata>
      <MDI key="STATISTICS_MAXIMUM">0.89550280570984</MDI>
      <MDI key="STATISTICS_MEAN">1.#SNAN</MDI>
      <MDI key="STATISTICS_MINIMUM">0.68621349334717</MDI>
      <MDI key="STATISTICS_STDDEV">1.#SNAN</MDI>
    </Metadata>
  </PAMRasterBand>
  <PAMRasterBand band="234">
    <Metadata>
      <MDI key="STATISTICS_MAXIMUM">0.90541732311249</MDI>
      <MDI key="STATISTICS_MEAN">1.#SNAN</MDI>
      <MDI key="STATISTICS_MINIMUM">0.66759765148163</MDI>
      <MDI key="STATISTICS_STDDEV">1.#SNAN</MDI>
    </Metadata>
  </PAMRasterBand>
  <PAMRasterBand band="235">
    <Metadata>
      <MDI key="STATISTICS_MAXIMUM">0.95667243003845</MDI>
      <MDI key="STATISTICS_MEAN">1.#SNAN</MDI>
      <MDI key="STATISTICS_MINIMUM">0.6969211101532</MDI>
      <MDI key="STATISTICS_STDDEV">1.#SNAN</MDI>
    </Metadata>
  </PAMRasterBand>
  <PAMRasterBand band="236">
    <Metadata>
      <MDI key="STATISTICS_MAXIMUM">0.95705789327621</MDI>
      <MDI key="STATISTICS_MEAN">1.#SNAN</MDI>
      <MDI key="STATISTICS_MINIMUM">0.69075179100037</MDI>
      <MDI key="STATISTICS_STDDEV">1.#SNAN</MDI>
    </Metadata>
  </PAMRasterBand>
  <PAMRasterBand band="237">
    <Metadata>
      <MDI key="STATISTICS_MAXIMUM">0.90632075071335</MDI>
      <MDI key="STATISTICS_MEAN">1.#SNAN</MDI>
      <MDI key="STATISTICS_MINIMUM">0.6236909031868</MDI>
      <MDI key="STATISTICS_STDDEV">1.#SNAN</MDI>
    </Metadata>
  </PAMRasterBand>
  <PAMRasterBand band="238">
    <Metadata>
      <MDI key="STATISTICS_MAXIMUM">0.94819229841232</MDI>
      <MDI key="STATISTICS_MEAN">1.#SNAN</MDI>
      <MDI key="STATISTICS_MINIMUM">0.68298161029816</MDI>
      <MDI key="STATISTICS_STDDEV">1.#SNAN</MDI>
    </Metadata>
  </PAMRasterBand>
  <PAMRasterBand band="239">
    <Metadata>
      <MDI key="STATISTICS_MAXIMUM">0.90301656723022</MDI>
      <MDI key="STATISTICS_MEAN">1.#SNAN</MDI>
      <MDI key="STATISTICS_MINIMUM">0.6549277305603</MDI>
      <MDI key="STATISTICS_STDDEV">1.#SNAN</MDI>
    </Metadata>
  </PAMRasterBand>
  <PAMRasterBand band="240">
    <Metadata>
      <MDI key="STATISTICS_MAXIMUM">0.946682035923</MDI>
      <MDI key="STATISTICS_MEAN">1.#SNAN</MDI>
      <MDI key="STATISTICS_MINIMUM">0.70350730419159</MDI>
      <MDI key="STATISTICS_STDDEV">1.#SNAN</MDI>
    </Metadata>
  </PAMRasterBand>
  <PAMRasterBand band="241">
    <Metadata>
      <MDI key="STATISTICS_MAXIMUM">0.93943023681641</MDI>
      <MDI key="STATISTICS_MEAN">1.#SNAN</MDI>
      <MDI key="STATISTICS_MINIMUM">0.7115963101387</MDI>
      <MDI key="STATISTICS_STDDEV">1.#SNAN</MDI>
    </Metadata>
  </PAMRasterBand>
  <PAMRasterBand band="242">
    <Metadata>
      <MDI key="STATISTICS_MAXIMUM">0.9178791642189</MDI>
      <MDI key="STATISTICS_MEAN">1.#SNAN</MDI>
      <MDI key="STATISTICS_MINIMUM">0.67324864864349</MDI>
      <MDI key="STATISTICS_STDDEV">1.#SNAN</MDI>
    </Metadata>
  </PAMRasterBand>
  <PAMRasterBand band="243">
    <Metadata>
      <MDI key="STATISTICS_MAXIMUM">0.93576544523239</MDI>
      <MDI key="STATISTICS_MEAN">1.#SNAN</MDI>
      <MDI key="STATISTICS_MINIMUM">0.72795385122299</MDI>
      <MDI key="STATISTICS_STDDEV">1.#SNAN</MDI>
    </Metadata>
  </PAMRasterBand>
  <PAMRasterBand band="244">
    <Metadata>
      <MDI key="STATISTICS_MAXIMUM">0.92291051149368</MDI>
      <MDI key="STATISTICS_MEAN">1.#SNAN</MDI>
      <MDI key="STATISTICS_MINIMUM">0.70174694061279</MDI>
      <MDI key="STATISTICS_STDDEV">1.#SNAN</MDI>
    </Metadata>
  </PAMRasterBand>
  <PAMRasterBand band="245">
    <Metadata>
      <MDI key="STATISTICS_MAXIMUM">0.99363505840302</MDI>
      <MDI key="STATISTICS_MEAN">1.#SNAN</MDI>
      <MDI key="STATISTICS_MINIMUM">0.73589181900024</MDI>
      <MDI key="STATISTICS_STDDEV">1.#SNAN</MDI>
    </Metadata>
  </PAMRasterBand>
  <PAMRasterBand band="246">
    <Metadata>
      <MDI key="STATISTICS_MAXIMUM">0.96814602613449</MDI>
      <MDI key="STATISTICS_MEAN">1.#SNAN</MDI>
      <MDI key="STATISTICS_MINIMUM">0.71452832221985</MDI>
      <MDI key="STATISTICS_STDDEV">1.#SNAN</MDI>
    </Metadata>
  </PAMRasterBand>
  <PAMRasterBand band="247">
    <Metadata>
      <MDI key="STATISTICS_MAXIMUM">0.95137137174606</MDI>
      <MDI key="STATISTICS_MEAN">1.#SNAN</MDI>
      <MDI key="STATISTICS_MINIMUM">0.68958610296249</MDI>
      <MDI key="STATISTICS_STDDEV">1.#SNAN</MDI>
    </Metadata>
  </PAMRasterBand>
  <PAMRasterBand band="248">
    <Metadata>
      <MDI key="STATISTICS_MAXIMUM">0.97203558683395</MDI>
      <MDI key="STATISTICS_MEAN">1.#SNAN</MDI>
      <MDI key="STATISTICS_MINIMUM">0.67860263586044</MDI>
      <MDI key="STATISTICS_STDDEV">1.#SNAN</MDI>
    </Metadata>
  </PAMRasterBand>
  <PAMRasterBand band="249">
    <Metadata>
      <MDI key="STATISTICS_MAXIMUM">0.94385808706284</MDI>
      <MDI key="STATISTICS_MEAN">1.#SNAN</MDI>
      <MDI key="STATISTICS_MINIMUM">0.69618427753448</MDI>
      <MDI key="STATISTICS_STDDEV">1.#SNAN</MDI>
    </Metadata>
  </PAMRasterBand>
  <PAMRasterBand band="250">
    <Metadata>
      <MDI key="STATISTICS_MAXIMUM">0.99071592092514</MDI>
      <MDI key="STATISTICS_MEAN">1.#SNAN</MDI>
      <MDI key="STATISTICS_MINIMUM">0.71776866912842</MDI>
      <MDI key="STATISTICS_STDDEV">1.#SNAN</MDI>
    </Metadata>
  </PAMRasterBand>
  <PAMRasterBand band="251">
    <Metadata>
      <MDI key="STATISTICS_MAXIMUM">0.91439682245255</MDI>
      <MDI key="STATISTICS_MEAN">1.#SNAN</MDI>
      <MDI key="STATISTICS_MINIMUM">0.67051267623901</MDI>
      <MDI key="STATISTICS_STDDEV">1.#SNAN</MDI>
    </Metadata>
  </PAMRasterBand>
  <PAMRasterBand band="252">
    <Metadata>
      <MDI key="STATISTICS_MAXIMUM">0.91544312238693</MDI>
      <MDI key="STATISTICS_MEAN">1.#SNAN</MDI>
      <MDI key="STATISTICS_MINIMUM">0.68363255262375</MDI>
      <MDI key="STATISTICS_STDDEV">1.#SNAN</MDI>
    </Metadata>
  </PAMRasterBand>
  <PAMRasterBand band="253">
    <Metadata>
      <MDI key="STATISTICS_MAXIMUM">1.0293145179749</MDI>
      <MDI key="STATISTICS_MEAN">1.#SNAN</MDI>
      <MDI key="STATISTICS_MINIMUM">0.72190660238266</MDI>
      <MDI key="STATISTICS_STDDEV">1.#SNAN</MDI>
    </Metadata>
  </PAMRasterBand>
  <PAMRasterBand band="254">
    <Metadata>
      <MDI key="STATISTICS_MAXIMUM">1.0257766246796</MDI>
      <MDI key="STATISTICS_MEAN">1.#SNAN</MDI>
      <MDI key="STATISTICS_MINIMUM">0.72547918558121</MDI>
      <MDI key="STATISTICS_STDDEV">1.#SNAN</MDI>
    </Metadata>
  </PAMRasterBand>
  <PAMRasterBand band="255">
    <Metadata>
      <MDI key="STATISTICS_MAXIMUM">1.0663281679153</MDI>
      <MDI key="STATISTICS_MEAN">1.#SNAN</MDI>
      <MDI key="STATISTICS_MINIMUM">0.67748188972473</MDI>
      <MDI key="STATISTICS_STDDEV">1.#SNAN</MDI>
    </Metadata>
  </PAMRasterBand>
  <PAMRasterBand band="256">
    <Metadata>
      <MDI key="STATISTICS_MAXIMUM">0.99448585510254</MDI>
      <MDI key="STATISTICS_MEAN">1.#SNAN</MDI>
      <MDI key="STATISTICS_MINIMUM">0.70940577983856</MDI>
      <MDI key="STATISTICS_STDDEV">1.#SNAN</MDI>
    </Metadata>
  </PAMRasterBand>
  <PAMRasterBand band="257">
    <Metadata>
      <MDI key="STATISTICS_MAXIMUM">0.92279011011124</MDI>
      <MDI key="STATISTICS_MEAN">1.#SNAN</MDI>
      <MDI key="STATISTICS_MINIMUM">0.62368780374527</MDI>
      <MDI key="STATISTICS_STDDEV">1.#SNAN</MDI>
    </Metadata>
  </PAMRasterBand>
  <PAMRasterBand band="258">
    <Metadata>
      <MDI key="STATISTICS_MAXIMUM">0.95432943105698</MDI>
      <MDI key="STATISTICS_MEAN">1.#SNAN</MDI>
      <MDI key="STATISTICS_MINIMUM">0.67446178197861</MDI>
      <MDI key="STATISTICS_STDDEV">1.#SNAN</MDI>
    </Metadata>
  </PAMRasterBand>
  <PAMRasterBand band="259">
    <Metadata>
      <MDI key="STATISTICS_MAXIMUM">0.9482649564743</MDI>
      <MDI key="STATISTICS_MEAN">1.#SNAN</MDI>
      <MDI key="STATISTICS_MINIMUM">0.67044639587402</MDI>
      <MDI key="STATISTICS_STDDEV">1.#SNAN</MDI>
    </Metadata>
  </PAMRasterBand>
  <PAMRasterBand band="260">
    <Metadata>
      <MDI key="STATISTICS_MAXIMUM">1.0093466043472</MDI>
      <MDI key="STATISTICS_MEAN">1.#SNAN</MDI>
      <MDI key="STATISTICS_MINIMUM">0.71745336055756</MDI>
      <MDI key="STATISTICS_STDDEV">1.#SNAN</MDI>
    </Metadata>
  </PAMRasterBand>
  <PAMRasterBand band="261">
    <Metadata>
      <MDI key="STATISTICS_MAXIMUM">1.1181690692902</MDI>
      <MDI key="STATISTICS_MEAN">1.#SNAN</MDI>
      <MDI key="STATISTICS_MINIMUM">0.7901439666748</MDI>
      <MDI key="STATISTICS_STDDEV">1.#SNAN</MDI>
    </Metadata>
  </PAMRasterBand>
  <PAMRasterBand band="262">
    <Metadata>
      <MDI key="STATISTICS_MAXIMUM">1.0394387245178</MDI>
      <MDI key="STATISTICS_MEAN">1.#SNAN</MDI>
      <MDI key="STATISTICS_MINIMUM">0.7215775847435</MDI>
      <MDI key="STATISTICS_STDDEV">1.#SNAN</MDI>
    </Metadata>
  </PAMRasterBand>
  <PAMRasterBand band="263">
    <Metadata>
      <MDI key="STATISTICS_MAXIMUM">0.92399019002914</MDI>
      <MDI key="STATISTICS_MEAN">1.#SNAN</MDI>
      <MDI key="STATISTICS_MINIMUM">0.61788707971573</MDI>
      <MDI key="STATISTICS_STDDEV">1.#SNAN</MDI>
    </Metadata>
  </PAMRasterBand>
  <PAMRasterBand band="264">
    <Metadata>
      <MDI key="STATISTICS_MAXIMUM">0.88512814044952</MDI>
      <MDI key="STATISTICS_MEAN">1.#SNAN</MDI>
      <MDI key="STATISTICS_MINIMUM">0.61874961853027</MDI>
      <MDI key="STATISTICS_STDDEV">1.#SNAN</MDI>
    </Metadata>
  </PAMRasterBand>
  <PAMRasterBand band="265">
    <Metadata>
      <MDI key="STATISTICS_MAXIMUM">1.0182337760925</MDI>
      <MDI key="STATISTICS_MEAN">1.#SNAN</MDI>
      <MDI key="STATISTICS_MINIMUM">0.68864208459854</MDI>
      <MDI key="STATISTICS_STDDEV">1.#SNAN</MDI>
    </Metadata>
  </PAMRasterBand>
  <PAMRasterBand band="266">
    <Metadata>
      <MDI key="STATISTICS_MAXIMUM">0.9866133928299</MDI>
      <MDI key="STATISTICS_MEAN">1.#SNAN</MDI>
      <MDI key="STATISTICS_MINIMUM">0.66587835550308</MDI>
      <MDI key="STATISTICS_STDDEV">1.#SNAN</MDI>
    </Metadata>
  </PAMRasterBand>
  <PAMRasterBand band="267">
    <Metadata>
      <MDI key="STATISTICS_MAXIMUM">0.9880513548851</MDI>
      <MDI key="STATISTICS_MEAN">1.#SNAN</MDI>
      <MDI key="STATISTICS_MINIMUM">0.65092539787292</MDI>
      <MDI key="STATISTICS_STDDEV">1.#SNAN</MDI>
    </Metadata>
  </PAMRasterBand>
  <PAMRasterBand band="268">
    <Metadata>
      <MDI key="STATISTICS_MAXIMUM">0.93764424324036</MDI>
      <MDI key="STATISTICS_MEAN">1.#SNAN</MDI>
      <MDI key="STATISTICS_MINIMUM">0.63353431224823</MDI>
      <MDI key="STATISTICS_STDDEV">1.#SNAN</MDI>
    </Metadata>
  </PAMRasterBand>
  <PAMRasterBand band="269">
    <Metadata>
      <MDI key="STATISTICS_MAXIMUM">1.1066445112228</MDI>
      <MDI key="STATISTICS_MEAN">1.#SNAN</MDI>
      <MDI key="STATISTICS_MINIMUM">0.7263371348381</MDI>
      <MDI key="STATISTICS_STDDEV">1.#SNAN</MDI>
    </Metadata>
  </PAMRasterBand>
  <PAMRasterBand band="270">
    <Metadata>
      <MDI key="STATISTICS_MAXIMUM">1.1418033838272</MDI>
      <MDI key="STATISTICS_MEAN">1.#SNAN</MDI>
      <MDI key="STATISTICS_MINIMUM">0.66197693347931</MDI>
      <MDI key="STATISTICS_STDDEV">1.#SNAN</MDI>
    </Metadata>
  </PAMRasterBand>
  <PAMRasterBand band="271">
    <Metadata>
      <MDI key="STATISTICS_MAXIMUM">1.1485139131546</MDI>
      <MDI key="STATISTICS_MEAN">1.#SNAN</MDI>
      <MDI key="STATISTICS_MINIMUM">0.62650936841965</MDI>
      <MDI key="STATISTICS_STDDEV">1.#SNAN</MDI>
    </Metadata>
  </PAMRasterBand>
  <PAMRasterBand band="272">
    <Metadata>
      <MDI key="STATISTICS_MAXIMUM">0.98780024051666</MDI>
      <MDI key="STATISTICS_MEAN">1.#SNAN</MDI>
      <MDI key="STATISTICS_MINIMUM">0.54810070991516</MDI>
      <MDI key="STATISTICS_STDDEV">1.#SNAN</MDI>
    </Metadata>
  </PAMRasterBand>
  <PAMRasterBand band="273">
    <Metadata>
      <MDI key="STATISTICS_MAXIMUM">1.0104349851608</MDI>
      <MDI key="STATISTICS_MEAN">1.#SNAN</MDI>
      <MDI key="STATISTICS_MINIMUM">0.56484389305115</MDI>
      <MDI key="STATISTICS_STDDEV">1.#SNAN</MDI>
    </Metadata>
  </PAMRasterBand>
  <PAMRasterBand band="274">
    <Metadata>
      <MDI key="STATISTICS_MAXIMUM">0.93435907363892</MDI>
      <MDI key="STATISTICS_MEAN">1.#SNAN</MDI>
      <MDI key="STATISTICS_MINIMUM">0.51075875759125</MDI>
      <MDI key="STATISTICS_STDDEV">1.#SNAN</MDI>
    </Metadata>
  </PAMRasterBand>
  <PAMRasterBand band="275">
    <Metadata>
      <MDI key="STATISTICS_MAXIMUM">0.95967590808868</MDI>
      <MDI key="STATISTICS_MEAN">1.#SNAN</MDI>
      <MDI key="STATISTICS_MINIMUM">0.53654646873474</MDI>
      <MDI key="STATISTICS_STDDEV">1.#SNAN</MDI>
    </Metadata>
  </PAMRasterBand>
  <PAMRasterBand band="276">
    <Metadata>
      <MDI key="STATISTICS_MAXIMUM">1.1469095945358</MDI>
      <MDI key="STATISTICS_MEAN">1.#SNAN</MDI>
      <MDI key="STATISTICS_MINIMUM">0.62825167179108</MDI>
      <MDI key="STATISTICS_STDDEV">1.#SNAN</MDI>
    </Metadata>
  </PAMRasterBand>
  <PAMRasterBand band="277">
    <Metadata>
      <MDI key="STATISTICS_MAXIMUM">1.0956826210022</MDI>
      <MDI key="STATISTICS_MEAN">1.#SNAN</MDI>
      <MDI key="STATISTICS_MINIMUM">0.52892857789993</MDI>
      <MDI key="STATISTICS_STDDEV">1.#SNAN</MDI>
    </Metadata>
  </PAMRasterBand>
  <PAMRasterBand band="278">
    <Metadata>
      <MDI key="STATISTICS_MAXIMUM">1.1949950456619</MDI>
      <MDI key="STATISTICS_MEAN">1.#SNAN</MDI>
      <MDI key="STATISTICS_MINIMUM">0.65060913562775</MDI>
      <MDI key="STATISTICS_STDDEV">1.#SNAN</MDI>
    </Metadata>
  </PAMRasterBand>
  <PAMRasterBand band="279">
    <Metadata>
      <MDI key="STATISTICS_MAXIMUM">1.0680948495865</MDI>
      <MDI key="STATISTICS_MEAN">1.#SNAN</MDI>
      <MDI key="STATISTICS_MINIMUM">0.56308805942535</MDI>
      <MDI key="STATISTICS_STDDEV">1.#SNAN</MDI>
    </Metadata>
  </PAMRasterBand>
  <PAMRasterBand band="280">
    <Metadata>
      <MDI key="STATISTICS_MAXIMUM">1.0877804756165</MDI>
      <MDI key="STATISTICS_MEAN">1.#SNAN</MDI>
      <MDI key="STATISTICS_MINIMUM">0.56866133213043</MDI>
      <MDI key="STATISTICS_STDDEV">1.#SNAN</MDI>
    </Metadata>
  </PAMRasterBand>
  <PAMRasterBand band="281">
    <Metadata>
      <MDI key="STATISTICS_MAXIMUM">1.1659801006317</MDI>
      <MDI key="STATISTICS_MEAN">1.#SNAN</MDI>
      <MDI key="STATISTICS_MINIMUM">0.5251317024231</MDI>
      <MDI key="STATISTICS_STDDEV">1.#SNAN</MDI>
    </Metadata>
  </PAMRasterBand>
  <PAMRasterBand band="282">
    <Metadata>
      <MDI key="STATISTICS_MAXIMUM">0.95061182975769</MDI>
      <MDI key="STATISTICS_MEAN">1.#SNAN</MDI>
      <MDI key="STATISTICS_MINIMUM">0.46575826406479</MDI>
      <MDI key="STATISTICS_STDDEV">1.#SNAN</MDI>
    </Metadata>
  </PAMRasterBand>
  <PAMRasterBand band="283">
    <Metadata>
      <MDI key="STATISTICS_MAXIMUM">1.228706240654</MDI>
      <MDI key="STATISTICS_MEAN">1.#SNAN</MDI>
      <MDI key="STATISTICS_MINIMUM">0.53986757993698</MDI>
      <MDI key="STATISTICS_STDDEV">1.#SNAN</MDI>
    </Metadata>
  </PAMRasterBand>
  <PAMRasterBand band="284">
    <Metadata>
      <MDI key="STATISTICS_MAXIMUM">0.9585462808609</MDI>
      <MDI key="STATISTICS_MEAN">1.#SNAN</MDI>
      <MDI key="STATISTICS_MINIMUM">0.48895043134689</MDI>
      <MDI key="STATISTICS_STDDEV">1.#SNAN</MDI>
    </Metadata>
  </PAMRasterBand>
  <PAMRasterBand band="285">
    <Metadata>
      <MDI key="STATISTICS_MAXIMUM">1.3264008760452</MDI>
      <MDI key="STATISTICS_MEAN">1.#SNAN</MDI>
      <MDI key="STATISTICS_MINIMUM">0.6351255774498</MDI>
      <MDI key="STATISTICS_STDDEV">1.#SNAN</MDI>
    </Metadata>
  </PAMRasterBand>
  <PAMRasterBand band="286">
    <Metadata>
      <MDI key="STATISTICS_MAXIMUM">0.99092167615891</MDI>
      <MDI key="STATISTICS_MEAN">1.#SNAN</MDI>
      <MDI key="STATISTICS_MINIMUM">0.4882228076458</MDI>
      <MDI key="STATISTICS_STDDEV">1.#SNAN</MDI>
    </Metadata>
  </PAMRasterBand>
  <PAMRasterBand band="287">
    <Metadata>
      <MDI key="STATISTICS_MAXIMUM">1.1406191587448</MDI>
      <MDI key="STATISTICS_MEAN">1.#SNAN</MDI>
      <MDI key="STATISTICS_MINIMUM">0.55065166950226</MDI>
      <MDI key="STATISTICS_STDDEV">1.#SNAN</MDI>
    </Metadata>
  </PAMRasterBand>
  <PAMRasterBand band="288">
    <Metadata>
      <MDI key="STATISTICS_MAXIMUM">1.0971846580505</MDI>
      <MDI key="STATISTICS_MEAN">1.#SNAN</MDI>
      <MDI key="STATISTICS_MINIMUM">0.44444540143013</MDI>
      <MDI key="STATISTICS_STDDEV">1.#SNAN</MDI>
    </Metadata>
  </PAMRasterBand>
  <PAMRasterBand band="289">
    <Metadata>
      <MDI key="STATISTICS_MAXIMUM">1.0652248859406</MDI>
      <MDI key="STATISTICS_MEAN">1.#SNAN</MDI>
      <MDI key="STATISTICS_MINIMUM">0.31201136112213</MDI>
      <MDI key="STATISTICS_STDDEV">1.#SNAN</MDI>
    </Metadata>
  </PAMRasterBand>
  <PAMRasterBand band="290">
    <Metadata>
      <MDI key="STATISTICS_MAXIMUM">1.3451583385468</MDI>
      <MDI key="STATISTICS_MEAN">1.#SNAN</MDI>
      <MDI key="STATISTICS_MINIMUM">0.21544432640076</MDI>
      <MDI key="STATISTICS_STDDEV">1.#SNAN</MDI>
    </Metadata>
  </PAMRasterBand>
  <PAMRasterBand band="291">
    <Metadata>
      <MDI key="STATISTICS_MAXIMUM">1.3011983633041</MDI>
      <MDI key="STATISTICS_MEAN">1.#SNAN</MDI>
      <MDI key="STATISTICS_MINIMUM">0.020080722868443</MDI>
      <MDI key="STATISTICS_STDDEV">1.#SNAN</MDI>
    </Metadata>
  </PAMRasterBand>
  <PAMRasterBand band="292">
    <Metadata>
      <MDI key="STATISTICS_MAXIMUM">1.0007214546204</MDI>
      <MDI key="STATISTICS_MEAN">1.#SNAN</MDI>
      <MDI key="STATISTICS_MINIMUM">0.041032053530216</MDI>
      <MDI key="STATISTICS_STDDEV">1.#SNAN</MDI>
    </Metadata>
  </PAMRasterBand>
  <PAMRasterBand band="293">
    <Metadata>
      <MDI key="STATISTICS_MAXIMUM">1.7114064693451</MDI>
      <MDI key="STATISTICS_MEAN">1.#SNAN</MDI>
      <MDI key="STATISTICS_MINIMUM">0.068755574524403</MDI>
      <MDI key="STATISTICS_STDDEV">1.#SNAN</MDI>
    </Metadata>
  </PAMRasterBand>
  <PAMRasterBand band="294">
    <Metadata>
      <MDI key="STATISTICS_MAXIMUM">1.4736082553864</MDI>
      <MDI key="STATISTICS_MEAN">1.#SNAN</MDI>
      <MDI key="STATISTICS_MINIMUM">0.039740309119225</MDI>
      <MDI key="STATISTICS_STDDEV">1.#SNAN</MDI>
    </Metadata>
  </PAMRasterBand>
  <PAMRasterBand band="295">
    <Metadata>
      <MDI key="STATISTICS_MAXIMUM">1.2736529111862</MDI>
      <MDI key="STATISTICS_MEAN">1.#SNAN</MDI>
      <MDI key="STATISTICS_MINIMUM">0.18237057328224</MDI>
      <MDI key="STATISTICS_STDDEV">1.#SNAN</MDI>
    </Metadata>
  </PAMRasterBand>
  <PAMRasterBand band="296">
    <Metadata>
      <MDI key="STATISTICS_MAXIMUM">1.4399255514145</MDI>
      <MDI key="STATISTICS_MEAN">1.#SNAN</MDI>
      <MDI key="STATISTICS_MINIMUM">0.10488305985928</MDI>
      <MDI key="STATISTICS_STDDEV">1.#SNAN</MDI>
    </Metadata>
  </PAMRasterBand>
  <PAMRasterBand band="297">
    <Metadata>
      <MDI key="STATISTICS_MAXIMUM">1.2499134540558</MDI>
      <MDI key="STATISTICS_MEAN">1.#SNAN</MDI>
      <MDI key="STATISTICS_MINIMUM">0.10034266859293</MDI>
      <MDI key="STATISTICS_STDDEV">1.#SNAN</MDI>
    </Metadata>
  </PAMRasterBand>
  <PAMRasterBand band="298">
    <Metadata>
      <MDI key="STATISTICS_MAXIMUM">1.7122759819031</MDI>
      <MDI key="STATISTICS_MEAN">1.#SNAN</MDI>
      <MDI key="STATISTICS_MINIMUM">0.013636164367199</MDI>
      <MDI key="STATISTICS_STDDEV">1.#SNAN</MDI>
    </Metadata>
  </PAMRasterBand>
  <PAMRasterBand band="299">
    <Metadata>
      <MDI key="STATISTICS_MAXIMUM">1.2209416627884</MDI>
      <MDI key="STATISTICS_MEAN">1.#SNAN</MDI>
      <MDI key="STATISTICS_MINIMUM">0</MDI>
      <MDI key="STATISTICS_STDDEV">1.#SNAN</MDI>
    </Metadata>
  </PAMRasterBand>
  <PAMRasterBand band="300">
    <Metadata>
      <MDI key="STATISTICS_MAXIMUM">1.1406185626984</MDI>
      <MDI key="STATISTICS_MEAN">1.#SNAN</MDI>
      <MDI key="STATISTICS_MINIMUM">0.019844578579068</MDI>
      <MDI key="STATISTICS_STDDEV">1.#SNAN</MDI>
    </Metadata>
  </PAMRasterBand>
  <PAMRasterBand band="301">
    <Metadata>
      <MDI key="STATISTICS_MAXIMUM">1.6742488145828</MDI>
      <MDI key="STATISTICS_MEAN">1.#SNAN</MDI>
      <MDI key="STATISTICS_MINIMUM">0.055925983935595</MDI>
      <MDI key="STATISTICS_STDDEV">1.#SNAN</MDI>
    </Metadata>
  </PAMRasterBand>
  <PAMRasterBand band="302">
    <Metadata>
      <MDI key="STATISTICS_MAXIMUM">1.2949973344803</MDI>
      <MDI key="STATISTICS_MEAN">1.#SNAN</MDI>
      <MDI key="STATISTICS_MINIMUM">0.096715569496155</MDI>
      <MDI key="STATISTICS_STDDEV">1.#SNAN</MDI>
    </Metadata>
  </PAMRasterBand>
  <PAMRasterBand band="303">
    <Metadata>
      <MDI key="STATISTICS_MAXIMUM">1.8472559452057</MDI>
      <MDI key="STATISTICS_MEAN">1.#SNAN</MDI>
      <MDI key="STATISTICS_MINIMUM">0.089018732309341</MDI>
      <MDI key="STATISTICS_STDDEV">1.#SNAN</MDI>
    </Metadata>
  </PAMRasterBand>
  <PAMRasterBand band="304">
    <Metadata>
      <MDI key="STATISTICS_MAXIMUM">1.4038699865341</MDI>
      <MDI key="STATISTICS_MEAN">1.#SNAN</MDI>
      <MDI key="STATISTICS_MINIMUM">0.033376760780811</MDI>
      <MDI key="STATISTICS_STDDEV">1.#SNAN</MDI>
    </Metadata>
  </PAMRasterBand>
  <PAMRasterBand band="305">
    <Metadata>
      <MDI key="STATISTICS_MAXIMUM">1.5906308889389</MDI>
      <MDI key="STATISTICS_MEAN">1.#SNAN</MDI>
      <MDI key="STATISTICS_MINIMUM">0.0663176253438</MDI>
      <MDI key="STATISTICS_STDDEV">1.#SNAN</MDI>
    </Metadata>
  </PAMRasterBand>
  <PAMRasterBand band="306">
    <Metadata>
      <MDI key="STATISTICS_MAXIMUM">1.0403853654861</MDI>
      <MDI key="STATISTICS_MEAN">1.#SNAN</MDI>
      <MDI key="STATISTICS_MINIMUM">0.032501757144928</MDI>
      <MDI key="STATISTICS_STDDEV">1.#SNAN</MDI>
    </Metadata>
  </PAMRasterBand>
  <PAMRasterBand band="307">
    <Metadata>
      <MDI key="STATISTICS_MAXIMUM">1.5389350652695</MDI>
      <MDI key="STATISTICS_MEAN">1.#SNAN</MDI>
      <MDI key="STATISTICS_MINIMUM">0.06836549192667</MDI>
      <MDI key="STATISTICS_STDDEV">1.#SNAN</MDI>
    </Metadata>
  </PAMRasterBand>
  <PAMRasterBand band="308">
    <Metadata>
      <MDI key="STATISTICS_MAXIMUM">0.93373012542725</MDI>
      <MDI key="STATISTICS_MEAN">1.#SNAN</MDI>
      <MDI key="STATISTICS_MINIMUM">0.01459548342973</MDI>
      <MDI key="STATISTICS_STDDEV">1.#SNAN</MDI>
    </Metadata>
  </PAMRasterBand>
  <PAMRasterBand band="309">
    <Metadata>
      <MDI key="STATISTICS_MAXIMUM">1.4475145339966</MDI>
      <MDI key="STATISTICS_MEAN">1.#SNAN</MDI>
      <MDI key="STATISTICS_MINIMUM">0.15204627811909</MDI>
      <MDI key="STATISTICS_STDDEV">1.#SNAN</MDI>
    </Metadata>
  </PAMRasterBand>
  <PAMRasterBand band="310">
    <Metadata>
      <MDI key="STATISTICS_MAXIMUM">1.3886328935623</MDI>
      <MDI key="STATISTICS_MEAN">1.#SNAN</MDI>
      <MDI key="STATISTICS_MINIMUM">0.1516193151474</MDI>
      <MDI key="STATISTICS_STDDEV">1.#SNAN</MDI>
    </Metadata>
  </PAMRasterBand>
  <PAMRasterBand band="311">
    <Metadata>
      <MDI key="STATISTICS_MAXIMUM">1.1796308755875</MDI>
      <MDI key="STATISTICS_MEAN">1.#SNAN</MDI>
      <MDI key="STATISTICS_MINIMUM">0.12104129046202</MDI>
      <MDI key="STATISTICS_STDDEV">1.#SNAN</MDI>
    </Metadata>
  </PAMRasterBand>
  <PAMRasterBand band="312">
    <Metadata>
      <MDI key="STATISTICS_MAXIMUM">1.23366355896</MDI>
      <MDI key="STATISTICS_MEAN">1.#SNAN</MDI>
      <MDI key="STATISTICS_MINIMUM">0.064965724945068</MDI>
      <MDI key="STATISTICS_STDDEV">1.#SNAN</MDI>
    </Metadata>
  </PAMRasterBand>
  <PAMRasterBand band="313">
    <Metadata>
      <MDI key="STATISTICS_MAXIMUM">1.0887793302536</MDI>
      <MDI key="STATISTICS_MEAN">1.#SNAN</MDI>
      <MDI key="STATISTICS_MINIMUM">0.024184348061681</MDI>
      <MDI key="STATISTICS_STDDEV">1.#SNAN</MDI>
    </Metadata>
  </PAMRasterBand>
  <PAMRasterBand band="314">
    <Metadata>
      <MDI key="STATISTICS_MAXIMUM">1.3341046571732</MDI>
      <MDI key="STATISTICS_MEAN">1.#SNAN</MDI>
      <MDI key="STATISTICS_MINIMUM">0.17719431221485</MDI>
      <MDI key="STATISTICS_STDDEV">1.#SNAN</MDI>
    </Metadata>
  </PAMRasterBand>
  <PAMRasterBand band="315">
    <Metadata>
      <MDI key="STATISTICS_MAXIMUM">1.1770290136337</MDI>
      <MDI key="STATISTICS_MEAN">1.#SNAN</MDI>
      <MDI key="STATISTICS_MINIMUM">0.038107715547085</MDI>
      <MDI key="STATISTICS_STDDEV">1.#SNAN</MDI>
    </Metadata>
  </PAMRasterBand>
  <PAMRasterBand band="316">
    <Metadata>
      <MDI key="STATISTICS_MAXIMUM">1.0911138057709</MDI>
      <MDI key="STATISTICS_MEAN">1.#SNAN</MDI>
      <MDI key="STATISTICS_MINIMUM">0.096990086138248</MDI>
      <MDI key="STATISTICS_STDDEV">1.#SNAN</MDI>
    </Metadata>
  </PAMRasterBand>
  <PAMRasterBand band="317">
    <Metadata>
      <MDI key="STATISTICS_MAXIMUM">1.2671446800232</MDI>
      <MDI key="STATISTICS_MEAN">1.#SNAN</MDI>
      <MDI key="STATISTICS_MINIMUM">0.043574888259172</MDI>
      <MDI key="STATISTICS_STDDEV">1.#SNAN</MDI>
    </Metadata>
  </PAMRasterBand>
  <PAMRasterBand band="318">
    <Metadata>
      <MDI key="STATISTICS_MAXIMUM">1.0666995048523</MDI>
      <MDI key="STATISTICS_MEAN">1.#SNAN</MDI>
      <MDI key="STATISTICS_MINIMUM">0.060109175741673</MDI>
      <MDI key="STATISTICS_STDDEV">1.#SNAN</MDI>
    </Metadata>
  </PAMRasterBand>
  <PAMRasterBand band="319">
    <Metadata>
      <MDI key="STATISTICS_MAXIMUM">1.1722096204758</MDI>
      <MDI key="STATISTICS_MEAN">1.#SNAN</MDI>
      <MDI key="STATISTICS_MINIMUM">0.074413701891899</MDI>
      <MDI key="STATISTICS_STDDEV">1.#SNAN</MDI>
    </Metadata>
  </PAMRasterBand>
  <PAMRasterBand band="320">
    <Metadata>
      <MDI key="STATISTICS_MAXIMUM">1.3601530790329</MDI>
      <MDI key="STATISTICS_MEAN">1.#SNAN</MDI>
      <MDI key="STATISTICS_MINIMUM">0.0014018408255652</MDI>
      <MDI key="STATISTICS_STDDEV">1.#SNAN</MDI>
    </Metadata>
  </PAMRasterBand>
  <PAMRasterBand band="321">
    <Metadata>
      <MDI key="STATISTICS_MAXIMUM">2.4586849212646</MDI>
      <MDI key="STATISTICS_MEAN">1.#SNAN</MDI>
      <MDI key="STATISTICS_MINIMUM">0.04703064262867</MDI>
      <MDI key="STATISTICS_STDDEV">1.#SNAN</MDI>
    </Metadata>
  </PAMRasterBand>
  <PAMRasterBand band="322">
    <Metadata>
      <MDI key="STATISTICS_MAXIMUM">1.3401427268982</MDI>
      <MDI key="STATISTICS_MEAN">1.#SNAN</MDI>
      <MDI key="STATISTICS_MINIMUM">0.055761072784662</MDI>
      <MDI key="STATISTICS_STDDEV">1.#SNAN</MDI>
    </Metadata>
  </PAMRasterBand>
  <PAMRasterBand band="323">
    <Metadata>
      <MDI key="STATISTICS_MAXIMUM">1.2540527582169</MDI>
      <MDI key="STATISTICS_MEAN">1.#SNAN</MDI>
      <MDI key="STATISTICS_MINIMUM">0.052054364234209</MDI>
      <MDI key="STATISTICS_STDDEV">1.#SNAN</MDI>
    </Metadata>
  </PAMRasterBand>
  <PAMRasterBand band="324">
    <Metadata>
      <MDI key="STATISTICS_MAXIMUM">1.0823479890823</MDI>
      <MDI key="STATISTICS_MEAN">1.#SNAN</MDI>
      <MDI key="STATISTICS_MINIMUM">0.062284521758556</MDI>
      <MDI key="STATISTICS_STDDEV">1.#SNAN</MDI>
    </Metadata>
  </PAMRasterBand>
  <PAMRasterBand band="325">
    <Metadata>
      <MDI key="STATISTICS_MAXIMUM">1.0789918899536</MDI>
      <MDI key="STATISTICS_MEAN">1.#SNAN</MDI>
      <MDI key="STATISTICS_MINIMUM">0.084921576082706</MDI>
      <MDI key="STATISTICS_STDDEV">1.#SNAN</MDI>
    </Metadata>
  </PAMRasterBand>
  <PAMRasterBand band="326">
    <Metadata>
      <MDI key="STATISTICS_MAXIMUM">1.3995056152344</MDI>
      <MDI key="STATISTICS_MEAN">1.#SNAN</MDI>
      <MDI key="STATISTICS_MINIMUM">0.010290124453604</MDI>
      <MDI key="STATISTICS_STDDEV">1.#SNAN</MDI>
    </Metadata>
  </PAMRasterBand>
</PAMDataset>
