<?xml version="1.0" encoding="UTF-8"?>
<RegionsOfInterest version="1.1">
  <Region name="A1" color="0,255,0">
    <GeometryDef>
      <CoordSysStr>GEOGCS["GCS_WGS_1984",DATUM["D_WGS_1984",SPHEROID["WGS_1984",6378137.0,298.257223563]],PRIMEM["Greenwich",0.0],UNIT["Degree",0.0174532925199433]]</CoordSysStr>
      <Polygon>
        <Exterior>
          <LinearRing>
            <Coordinates>
-68.0004697 44.73333819 -68.00046892 44.73333823 -68.00046861 44.73333739 -68.00047027 44.73333727 -68.00047004 44.73333786 -68.0004697 44.73333819
            </Coordinates>
          </LinearRing>
        </Exterior>
      </Polygon>
    </GeometryDef>
  </Region>
  <Region name="A2" color="0,255,0">
    <GeometryDef>
      <CoordSysStr>GEOGCS["GCS_WGS_1984",DATUM["D_WGS_1984",SPHEROID["WGS_1984",6378137.0,298.257223563]],PRIMEM["Greenwich",0.0],UNIT["Degree",0.0174532925199433]]</CoordSysStr>
      <Polygon>
        <Exterior>
          <LinearRing>
            <Coordinates>
-68.00010401 44.73324017 -68.00010317 44.73324014 -68.00010316 44.73323943 -68.00010401 44.73323939 -68.00010423 44.73324012 -68.00010401 44.73324017
            </Coordinates>
          </LinearRing>
        </Exterior>
      </Polygon>
    </GeometryDef>
  </Region>
</RegionsOfInterest>
